Workbook

Sheet A
A1: NOMBRE APELLIDO | B1: -2=EsBalada, -1=PareceBalada, 1=PareceRegeatton, 2=EsRegaetton | C1: FRAGMENTO DE LETRAS DE CANCIONES (ALREDEDOR DE 30+ PALABRAS)
A2: EDGAR CASASOLA | B2: -1 | C2: ¿A quién le mientes si en tu soledad? Quieres verme otra vez Por ti respondo lo que tú me das Lo que nadie sabe Me decido por ti, te decides por mí A la misma hora Me dan ganas de ti, te dan ganas de mí A la misma hora
A3: DANIEL SEQUEIRA APUY | B3: 2 | C3: ¿Cómo te llamas, baby? Desde que te vi supe que eras pa’ mí Dile a tus amigas que andamo' ready Esto lo seguimo' en el after party
A4: ESTEBAN HIGUERA | B4: -2 | C4: ¿Cómo te va, mi amor? ¿Cómo te va? Era en silencio la pregunta entre tú y yo ¿Eres feliz, mi bien? Sin engañar Porque a mi puerta el amor nunca volvió
A5: Adrian Arrieta Orozco | B5: 2 | C5: ¿Pa' qué buscar en la calle lo que abunda en mi casa? Una mamacita buena gente, qué chimba de cuerpo y de cara. Y aunque la baby es inocente y con otras se compara. Diosito la hizo humilde, pero yo la veo bien cara
A6: Andres Camacho | B6: 0 | C6: ¿Por qué sigues con él? (¿Por qué sigues con él?) Si borracha me confesaste que él no te lo hace bien Tú le calientas la comida, pero él no te sabe comer (okay) Si pruebas, no vas a volver (no), no, yeh
A7: DANIEL SEQUEIRA APUY | B7: 1 | C7: ¿Qué hace' tan triste y solita? Recuerdo, feliz, tu carita Me busca si me necesita Conmigo, te puede' desahogar
A8: Matias Casasola | B8: -1 | C8: ¿Qué más puedo decirte? Tal vez puedo mentirte sin razón Pero lo que hoy siento Es que sin ti, estoy muerto, pues eres Lo que más quiero en este mundo, eso eres
A9: DENNIS CAMACHO SOTO | B9: 2 | C9: ¿Qué me hizo usted? Que la quiero volver a ver Y volverla a besar Yo te paso a buscar, buscar Es que la bellaquera contigo Con nadie más la consigo De tus grito' hoy no me olvido Te-te-tengo reservao' el hotel
A10: IVAN RIOS BALTODANO | B10: -2 | C10: ¿Qué tienen tus ojos, tus labios, tu piel Que nunca se acaba esta luna de miel? Somos la copa y el vino Tú y yo vamos juntos desde que nos vimos Subimos, bajamos, lloramos, reímos Y es que contigo, mi amor, todo me sabe mejor
A11: DENNIS CAMACHO SOTO | B11: -2 | C11: ¿Y quién te escribirá poemas y cartas? ¿Y quién te contará sus miedos y faltas? ¿A quién le dejarás dormirse en tu espalda? Y luego en el silencio le dirás "te quiero" Detendrá su aliento sobre tu cara Perderá su rumbo en tu mirada Y se le olvidará la vida amándote ¿Ahora quién?
A12: KONSTANTIN LATYSH | B12: 1 | C12: "Ella no era así, ella no era así No sé quién la dañó Ella no era así, ella no era así No sé quién la dañó"
A13: Matias Casasola | B13: 2 | C13: (¿Pa' qué me estás llamando?) Dime si es verdad que él te trae loca (¿Y a vos qué te importa?) (¿Ah, sí?) Aún no lo creo, en tan poco tiempo y ya besas otra boca ¡De malas! (¿Qué?) Dime cuál fue mi error (dime) Si mi único delito solo fue amarte Hoy soy el perdedor (bebé, nomás) Y él me ha robado el truco para enamorarte (¿qué pasa, mi amor?)
... A691: Arturo Daniels Fernández | B691: 2 | C691: Zúmbale mambo, pa' que mis gatas prendan los motore' Zúmbale mambo, pa' que mis gatas prendan los motore' Zúmbale mambo, pa' que mis gatas prendan los motore' Que se preparen, que lo que viene es pa' que le den (¡duro!) Mamita, yo sé que tú no te me vas a quitar (¡duro!) Lo que me gusta es que tú te dejas llevar (¡duro!) Todos los weekend, ella sale a vacilar (¡duro!) Mi gata no para de janguear, porque

Sheet B
A1: NOMBRE APELLIDO | B1: -2=EsBalada, -1=PareceBalada, 1=PareceRegeatton, 2=EsRegaetton | C1: FRAGMENTO DE LETRAS DE CANCIONES (ALREDEDOR DE 30+ PALABRAS)
A2: MINOR SANDI | B2: -2 | C2: ¿A quién le mientes si en tu soledad? Quieres verme otra vez Por ti respondo lo que tú me das Lo que nadie sabe Me decido por ti, te decides por mí A la misma hora Me dan ganas de ti, te dan ganas de mí A la misma hora
A3: Sawyer Dixon | B3: 2 | C3: ¿Cómo te llamas, baby? Desde que te vi supe que eras pa’ mí Dile a tus amigas que andamo' ready Esto lo seguimo' en el after party
A4: Andres Camacho | B4: 0 | C4: ¿Cómo te va, mi amor? ¿Cómo te va? Era en silencio la pregunta entre tú y yo ¿Eres feliz, mi bien? Sin engañar Porque a mi puerta el amor nunca volvió
A5: EVAN CHEN | B5: 2 | C5: ¿Pa' qué buscar en la calle lo que abunda en mi casa? Una mamacita buena gente, qué chimba de cuerpo y de cara. Y aunque la baby es inocente y con otras se compara. Diosito la hizo humilde, pero yo la veo bien cara
A6: DENNIS CAMACHO SOTO | B6: 2 | C6: ¿Por qué sigues con él? (¿Por qué sigues con él?) Si borracha me confesaste que él no te lo hace bien Tú le calientas la comida, pero él no te sabe comer (okay) Si pruebas, no vas a volver (no), no, yeh
A7: Juan Pablo Vindas | B7: 0 | C7: ¿Qué hace' tan triste y solita? Recuerdo, feliz, tu carita Me busca si me necesita Conmigo, te puede' desahogar
A8: KONSTANTIN LATYSH | B8: -2 | C8: ¿Qué más puedo decirte? Tal vez puedo mentirte sin razón Pero lo que hoy siento Es que sin ti, estoy muerto, pues eres Lo que más quiero en este mundo, eso eres
A9: ENRIQUE RAMÍREZ | B9: 2 | C9: ¿Qué me hizo usted? Que la quiero volver a ver Y volverla a besar Yo te paso a buscar, buscar Es que la bellaquera contigo Con nadie más la consigo De tus grito' hoy no me olvido Te-te-tengo reservao' el hotel
A10: Juan Diego Gauthier Sandoval | B10: -2 | C10: ¿Qué tienen tus ojos, tus labios, tu piel Que nunca se acaba esta luna de miel? Somos la copa y el vino Tú y yo vamos juntos desde que nos vimos Subimos, bajamos, lloramos, reímos Y es que contigo, mi amor, todo me sabe mejor
A11: Sawyer Dixon | B11: -2 | C11: ¿Y quién te escribirá poemas y cartas? ¿Y quién te contará sus miedos y faltas? ¿A quién le dejarás dormirse en tu espalda? Y luego en el silencio le dirás "te quiero" Detendrá su aliento sobre tu cara Perderá su rumbo en tu mirada Y se le olvidará la vida amándote ¿Ahora quién?
A12: Arturo Daniels Fernández | B12: 1 | C12: "Ella no era así, ella no era así No sé quién la dañó Ella no era así, ella no era así No sé quién la dañó"
A13: Anabelle Porras Carrillo | B13: 2 | C13: (¿Pa' qué me estás llamando?) Dime si es verdad que él te trae loca (¿Y a vos qué te importa?) (¿Ah, sí?) Aún no lo creo, en tan poco tiempo y ya besas otra boca ¡De malas! (¿Qué?) Dime cuál fue mi error (dime) Si mi único delito solo fue amarte Hoy soy el perdedor (bebé, nomás) Y él me ha robado el truco para enamorarte (¿qué pasa, mi amor?)
... A691: Leonardo Sibaja Campos | B691: 2 | C691: Zúmbale mambo, pa' que mis gatas prendan los motore' Zúmbale mambo, pa' que mis gatas prendan los motore' Zúmbale mambo, pa' que mis gatas prendan los motore' Que se preparen, que lo que viene es pa' que le den (¡duro!) Mamita, yo sé que tú no te me vas a quitar (¡duro!) Lo que me gusta es que tú te dejas llevar (¡duro!) Todos los weekend, ella sale a vacilar (¡duro!) Mi gata no para de janguear, porque

Sheet C
A1: NOMBRE APELLIDO | B1: -2=EsBalada, -1=PareceBalada, 1=PareceRegeatton, 2=EsRegaetton | C1: FRAGMENTO DE LETRAS DE CANCIONES (ALREDEDOR DE 30+ PALABRAS)
A2: Arturo Daniels Fernández | B2: -1 | C2: ¿A quién le mientes si en tu soledad? Quieres verme otra vez Por ti respondo lo que tú me das Lo que nadie sabe Me decido por ti, te decides por mí A la misma hora Me dan ganas de ti, te dan ganas de mí A la misma hora
A3: IVAN RIOS BALTODANO | B3: 2 | C3: ¿Cómo te llamas, baby? Desde que te vi supe que eras pa’ mí Dile a tus amigas que andamo' ready Esto lo seguimo' en el after party
A4: EVAN CHEN | B4: -1 | C4: ¿Cómo te va, mi amor? ¿Cómo te va? Era en silencio la pregunta entre tú y yo ¿Eres feliz, mi bien? Sin engañar Porque a mi puerta el amor nunca volvió
A5: EDGAR CASASOLA | B5: 2 | C5: ¿Pa' qué buscar en la calle lo que abunda en mi casa? Una mamacita buena gente, qué chimba de cuerpo y de cara. Y aunque la baby es inocente y con otras se compara. Diosito la hizo humilde, pero yo la veo bien cara
A6: ENRIQUE RAMÍREZ | B6: 2 | C6: ¿Por qué sigues con él? (¿Por qué sigues con él?) Si borracha me confesaste que él no te lo hace bien Tú le calientas la comida, pero él no te sabe comer (okay) Si pruebas, no vas a volver (no), no, yeh
A7: Arturo Daniels Fernández | B7: 2 | C7: ¿Qué hace' tan triste y solita? Recuerdo, feliz, tu carita Me busca si me necesita Conmigo, te puede' desahogar
A8: Anthony Sanchez | B8: -2 | C8: ¿Qué más puedo decirte? Tal vez puedo mentirte sin razón Pero lo que hoy siento Es que sin ti, estoy muerto, pues eres Lo que más quiero en este mundo, eso eres
A9: Mauro Valenciano | B9: 2 | C9: ¿Qué me hizo usted? Que la quiero volver a ver Y volverla a besar Yo te paso a buscar, buscar Es que la bellaquera contigo Con nadie más la consigo De tus grito' hoy no me olvido Te-te-tengo reservao' el hotel
A10: Isabel Gómez | B10: -1 | C10: ¿Qué tienen tus ojos, tus labios, tu piel Que nunca se acaba esta luna de miel? Somos la copa y el vino Tú y yo vamos juntos desde que nos vimos Subimos, bajamos, lloramos, reímos Y es que contigo, mi amor, todo me sabe mejor
A11: ESTEBAN ROMÁN OVIEDO | B11: 0 | C11: ¿Y quién te escribirá poemas y cartas? ¿Y quién te contará sus miedos y faltas? ¿A quién le dejarás dormirse en tu espalda? Y luego en el silencio le dirás "te quiero" Detendrá su aliento sobre tu cara Perderá su rumbo en tu mirada Y se le olvidará la vida amándote ¿Ahora quién?
A12: Anabelle Porras Carrillo | B12: -1 | C12: "Ella no era así, ella no era así No sé quién la dañó Ella no era así, ella no era así No sé quién la dañó"
A13: BRANDON PALACIOS DELGADO | B13: 2 | C13: (¿Pa' qué me estás llamando?) Dime si es verdad que él te trae loca (¿Y a vos qué te importa?) (¿Ah, sí?) Aún no lo creo, en tan poco tiempo y ya besas otra boca ¡De malas! (¿Qué?) Dime cuál fue mi error (dime) Si mi único delito solo fue amarte Hoy soy el perdedor (bebé, nomás) Y él me ha robado el truco para enamorarte (¿qué pasa, mi amor?)
... A691: LUIS ARIAS GÓMEZ | B691: 2 | C691: Zúmbale mambo, pa' que mis gatas prendan los motore' Zúmbale mambo, pa' que mis gatas prendan los motore' Zúmbale mambo, pa' que mis gatas prendan los motore' Que se preparen, que lo que viene es pa' que le den (¡duro!) Mamita, yo sé que tú no te me vas a quitar (¡duro!) Lo que me gusta es que tú te dejas llevar (¡duro!) Todos los weekend, ella sale a vacilar (¡duro!) Mi gata no para de janguear, porque

Sheet AGREEMENT
A1: CATEGORIA | B1: AGREEMENT SCORE | C1: =A!A1 -> NOMBRE APELLIDO | D1: =A!B1 -> -2=EsBalada, -1=PareceBalada, 1=PareceRegeatton, 2=EsRegaetton | E1: =A!C1 -> FRAGMENTO DE LETRAS DE CANCIONES (ALREDEDOR DE 30+ PALABRAS) | F1: =B!A1 -> NOMBRE APELLIDO | G1: =B!B1 -> -2=EsBalada, -1=PareceBalada, 1=PareceRegeatton, 2=EsRegaetton | H1: =B!C1 -> FRAGMENTO DE LETRAS DE CANCIONES (ALREDEDOR DE 30+ PALABRAS) | I1: ='C'!A1 -> NOMBRE APELLIDO | J1: ='C'!B1 -> -2=EsBalada, -1=PareceBalada, 1=PareceRegeatton, 2=EsRegaetton | K1: ='C'!C1 -> FRAGMENTO DE LETRAS DE CANCIONES (ALREDEDOR DE 30+ PALABRAS) | L1: EXTRA | M1: CRITERIO | N1: VOTO EXTRA
A2: =IF(B2>0,"REGAETTON","BALADA") -> BALADA | B2: =SUM(D2,G2,J2,N2) -> -4 | C2: =A!A2 -> EDGAR CASASOLA | D2: =A!B2 -> -1 | E2: =A!C2 -> ¿A quién le mientes si en tu soledad? Quieres verme otra vez Por ti respondo lo que tú me das Lo que nadie sabe Me decido por ti, te decides por mí A la misma hora Me dan ganas de ti, te dan ganas de mí A la misma hora | F2: =B!A2 -> MINOR SANDI | G2: =B!B2 -> -2 | H2: =B!C2 -> ¿A quién le mientes si en tu soledad? Quieres verme otra vez Por ti respondo lo que tú me das Lo que nadie sabe Me decido por ti, te decides por mí A la misma hora Me dan ganas de ti, te dan ganas de mí A la misma hora | I2: ='C'!A2 -> Arturo Daniels Fernández | J2: ='C'!B2 -> -1 | K2: ='C'!C2 -> ¿A quién le mientes si en tu soledad? Quieres verme otra vez Por ti respondo lo que tú me das Lo que nadie sabe Me decido por ti, te decides por mí A la misma hora Me dan ganas de ti, te dan ganas de mí A la misma hora | M2: =IF(B2=0,"X"," ") | N2: 0
A3: =IF(B3>0,"REGAETTON","BALADA") -> REGAETTON | B3: =SUM(D3,G3,J3,N3) -> 6 | C3: =A!A3 -> DANIEL SEQUEIRA APUY | D3: =A!B3 -> 2 | E3: =A!C3 -> ¿Cómo te llamas, baby? Desde que te vi supe que eras pa’ mí Dile a tus amigas que andamo' ready Esto lo seguimo' en el after party | F3: =B!A3 -> Sawyer Dixon | G3: =B!B3 -> 2 | H3: =B!C3 -> ¿Cómo te llamas, baby? Desde que te vi supe que eras pa’ mí Dile a tus amigas que andamo' ready Esto lo seguimo' en el after party | I3: ='C'!A3 -> IVAN RIOS BALTODANO | J3: ='C'!B3 -> 2 | K3: ='C'!C3 -> ¿Cómo te llamas, baby? Desde que te vi supe que eras pa’ mí Dile a tus amigas que andamo' ready Esto lo seguimo' en el after party | M3: =IF(B3=0,"X"," ") | N3: 0
A4: =IF(B4>0,"REGAETTON","BALADA") -> BALADA | B4: =SUM(D4,G4,J4,N4) -> -3 | C4: =A!A4 -> ESTEBAN HIGUERA | D4: =A!B4 -> -2 | E4: =A!C4 -> ¿Cómo te va, mi amor? ¿Cómo te va? Era en silencio la pregunta entre tú y yo ¿Eres feliz, mi bien? Sin engañar Porque a mi puerta el amor nunca volvió | F4: =B!A4 -> Andres Camacho | G4: =B!B4 -> 0 | H4: =B!C4 -> ¿Cómo te va, mi amor? ¿Cómo te va? Era en silencio la pregunta entre tú y yo ¿Eres feliz, mi bien? Sin engañar Porque a mi puerta el amor nunca volvió | I4: ='C'!A4 -> EVAN CHEN | J4: ='C'!B4 -> -1 | K4: ='C'!C4 -> ¿Cómo te va, mi amor? ¿Cómo te va? Era en silencio la pregunta entre tú y yo ¿Eres feliz, mi bien? Sin engañar Porque a mi puerta el amor nunca volvió | M4: =IF(B4=0,"X"," ") | N4: 0
A5: =IF(B5>0,"REGAETTON","BALADA") -> REGAETTON | B5: =SUM(D5,G5,J5,N5) -> 6 | C5: =A!A5 -> Adrian Arrieta Orozco | D5: =A!B5 -> 2 | E5: =A!C5 -> ¿Pa' qué buscar en la calle lo que abunda en mi casa? Una mamacita buena gente, qué chimba de cuerpo y de cara. Y aunque la baby es inocente y con otras se compara. Diosito la hizo humilde, pero yo la veo bien cara | F5: =B!A5 -> EVAN CHEN | G5: =B!B5 -> 2 | H5: =B!C5 -> ¿Pa' qué buscar en la calle lo que abunda en mi casa? Una mamacita buena gente, qué chimba de cuerpo y de cara. Y aunque la baby es inocente y con otras se compara. Diosito la hizo humilde, pero yo la veo bien cara | I5: ='C'!A5 -> EDGAR CASASOLA | J5: ='C'!B5 -> 2 | K5: ='C'!C5 -> ¿Pa' qué buscar en la calle lo que abunda en mi casa? Una mamacita buena gente, qué chimba de cuerpo y de cara. Y aunque la baby es inocente y con otras se compara. Diosito la hizo humilde, pero yo la veo bien cara | M5: =IF(B5=0,"X"," ") | N5: 0
A6: =IF(B6>0,"REGAETTON","BALADA") -> REGAETTON | B6: =SUM(D6,G6,J6,N6) -> 4 | C6: =A!A6 -> Andres Camacho | D6: =A!B6 -> 0 | E6: =A!C6 -> ¿Por qué sigues con él? (¿Por qué sigues con él?) Si borracha me confesaste que él no te lo hace bien Tú le calientas la comida, pero él no te sabe comer (okay) Si pruebas, no vas a volver (no), no, yeh | F6: =B!A6 -> DENNIS CAMACHO SOTO | G6: =B!B6 -> 2 | H6: =B!C6 -> ¿Por qué sigues con él? (¿Por qué sigues con él?) Si borracha me confesaste que él no te lo hace bien Tú le calientas la comida, pero él no te sabe comer (okay) Si pruebas, no vas a volver (no), no, yeh | I6: ='C'!A6 -> ENRIQUE RAMÍREZ | J6: ='C'!B6 -> 2 | K6: ='C'!C6 -> ¿Por qué sigues con él? (¿Por qué sigues con él?) Si borracha me confesaste que él no te lo hace bien Tú le calientas la comida, pero él no te sabe comer (okay) Si pruebas, no vas a volver (no), no, yeh | M6: =IF(B6=0,"X"," ") | N6: 0
A7: =IF(B7>0,"REGAETTON","BALADA") -> REGAETTON | B7: =SUM(D7,G7,J7,N7) -> 3 | C7: =A!A7 -> DANIEL SEQUEIRA APUY | D7: =A!B7 -> 1 | E7: =A!C7 -> ¿Qué hace' tan triste y solita? Recuerdo, feliz, tu carita Me busca si me necesita Conmigo, te puede' desahogar | F7: =B!A7 -> Juan Pablo Vindas | G7: =B!B7 -> 0 | H7: =B!C7 -> ¿Qué hace' tan triste y solita? Recuerdo, feliz, tu carita Me busca si me necesita Conmigo, te puede' desahogar | I7: ='C'!A7 -> Arturo Daniels Fernández | J7: ='C'!B7 -> 2 | K7: ='C'!C7 -> ¿Qué hace' tan triste y solita? Recuerdo, feliz, tu carita Me busca si me necesita Conmigo, te puede' desahogar | M7: =IF(B7=0,"X"," ") | N7: 0
A8: =IF(B8>0,"REGAETTON","BALADA") -> BALADA | B8: =SUM(D8,G8,J8,N8) -> -5 | C8: =A!A8 -> Matias Casasola | D8: =A!B8 -> -1 | E8: =A!C8 -> ¿Qué más puedo decirte? Tal vez puedo mentirte sin razón Pero lo que hoy siento Es que sin ti, estoy muerto, pues eres Lo que más quiero en este mundo, eso eres | F8: =B!A8 -> KONSTANTIN LATYSH | G8: =B!B8 -> -2 | H8: =B!C8 -> ¿Qué más puedo decirte? Tal vez puedo mentirte sin razón Pero lo que hoy siento Es que sin ti, estoy muerto, pues eres Lo que más quiero en este mundo, eso eres | I8: ='C'!A8 -> Anthony Sanchez | J8: ='C'!B8 -> -2 | K8: ='C'!C8 -> ¿Qué más puedo decirte? Tal vez puedo mentirte sin razón Pero lo que hoy siento Es que sin ti, estoy muerto, pues eres Lo que más quiero en este mundo, eso eres | M8: =IF(B8=0,"X"," ") | N8: 0
A9: =IF(B9>0,"REGAETTON","BALADA") -> REGAETTON | B9: =SUM(D9,G9,J9,N9) -> 6 | C9: =A!A9 -> DENNIS CAMACHO SOTO | D9: =A!B9 -> 2 | E9: =A!C9 -> ¿Qué me hizo usted? Que la quiero volver a ver Y volverla a besar Yo te paso a buscar, buscar Es que la bellaquera contigo Con nadie más la consigo De tus grito' hoy no me olvido Te-te-tengo reservao' el hotel | F9: =B!A9 -> ENRIQUE RAMÍREZ | G9: =B!B9 -> 2 | H9: =B!C9 -> ¿Qué me hizo usted? Que la quiero volver a ver Y volverla a besar Yo te paso a buscar, buscar Es que la bellaquera contigo Con nadie más la consigo De tus grito' hoy no me olvido Te-te-tengo reservao' el hotel | I9: ='C'!A9 -> Mauro Valenciano | J9: ='C'!B9 -> 2 | K9: ='C'!C9 -> ¿Qué me hizo usted? Que la quiero volver a ver Y volverla a besar Yo te paso a buscar, buscar Es que la bellaquera contigo Con nadie más la consigo De tus grito' hoy no me olvido Te-te-tengo reservao' el hotel | M9: =IF(B9=0,"X"," ") | N9: 0
A10: =IF(B10>0,"REGAETTON","BALADA") -> BALADA | B10: =SUM(D10,G10,J10,N10) -> -5 | C10: =A!A10 -> IVAN RIOS BALTODANO | D10: =A!B10 -> -2 | E10: =A!C10 -> ¿Qué tienen tus ojos, tus labios, tu piel Que nunca se acaba esta luna de miel? Somos la copa y el vino Tú y yo vamos juntos desde que nos vimos Subimos, bajamos, lloramos, reímos Y es que contigo, mi amor, todo me sabe mejor | F10: =B!A10 -> Juan Diego Gauthier Sandoval | G10: =B!B10 -> -2 | H10: =B!C10 -> ¿Qué tienen tus ojos, tus labios, tu piel Que nunca se acaba esta luna de miel? Somos la copa y el vino Tú y yo vamos juntos desde que nos vimos Subimos, bajamos, lloramos, reímos Y es que contigo, mi amor, todo me sabe mejor | I10: ='C'!A10 -> Isabel Gómez | J10: ='C'!B10 -> -1 | K10: ='C'!C10 -> ¿Qué tienen tus ojos, tus labios, tu piel Que nunca se acaba esta luna de miel? Somos la copa y el vino Tú y yo vamos juntos desde que nos vimos Subimos, bajamos, lloramos, reímos Y es que contigo, mi amor, todo me sabe mejor | M10: =IF(B10=0,"X"," ") | N10: 0
A11: =IF(B11>0,"REGAETTON","BALADA") -> BALADA | B11: =SUM(D11,G11,J11,N11) -> -4 | C11: =A!A11 -> DENNIS CAMACHO SOTO | D11: =A!B11 -> -2 | E11: =A!C11 -> ¿Y quién te escribirá poemas y cartas? ¿Y quién te contará sus miedos y faltas? ¿A quién le dejarás dormirse en tu espalda? Y luego en el silencio le dirás "te quiero" Detendrá su aliento sobre tu cara Perderá su rumbo en tu mirada Y se le olvidará la vida amándote ¿Ahora quién? | F11: =B!A11 -> Sawyer Dixon | G11: =B!B11 -> -2 | H11: =B!C11 -> ¿Y quién te escribirá poemas y cartas? ¿Y quién te contará sus miedos y faltas? ¿A quién le dejarás dormirse en tu espalda? Y luego en el silencio le dirás "te quiero" Detendrá su aliento sobre tu cara Perderá su rumbo en tu mirada Y se le olvidará la vida amándote ¿Ahora quién? | I11: ='C'!A11 -> ESTEBAN ROMÁN OVIEDO | J11: ='C'!B11 -> 0 | K11: ='C'!C11 -> ¿Y quién te escribirá poemas y cartas? ¿Y quién te contará sus miedos y faltas? ¿A quién le dejarás dormirse en tu espalda? Y luego en el silencio le dirás "te quiero" Detendrá su aliento sobre tu cara Perderá su rumbo en tu mirada Y se le olvidará la vida amándote ¿Ahora quién? | M11: =IF(B11=0,"X"," ") | N11: 0
A12: =IF(B12>0,"REGAETTON","BALADA") -> REGAETTON | B12: =SUM(D12,G12,J12,N12) -> 1 | C12: =A!A12 -> KONSTANTIN LATYSH | D12: =A!B12 -> 1 | E12: =A!C12 -> "Ella no era así, ella no era así No sé quién la dañó Ella no era así, ella no era así No sé quién la dañó" | F12: =B!A12 -> Arturo Daniels Fernández | G12: =B!B12 -> 1 | H12: =B!C12 -> "Ella no era así, ella no era así No sé quién la dañó Ella no era así, ella no era así No sé quién la dañó" | I12: ='C'!A12 -> Anabelle Porras Carrillo | J12: ='C'!B12 -> -1 | K12: ='C'!C12 -> "Ella no era así, ella no era así No sé quién la dañó Ella no era así, ella no era así No sé quién la dañó" | M12: =IF(B12=0,"X"," ") | N12: 0
A13: =IF(B13>0,"REGAETTON","BALADA") -> REGAETTON | B13: =SUM(D13,G13,J13,N13) -> 6 | C13: =A!A13 -> Matias Casasola | D13: =A!B13 -> 2 | E13: =A!C13 -> (¿Pa' qué me estás llamando?) Dime si es verdad que él te trae loca (¿Y a vos qué te importa?) (¿Ah, sí?) Aún no lo creo, en tan poco tiempo y ya besas otra boca ¡De malas! (¿Qué?) Dime cuál fue mi error (dime) Si mi único delito solo fue amarte Hoy soy el perdedor (bebé, nomás) Y él me ha robado el truco para enamorarte (¿qué pasa, mi amor?) | F13: =B!A13 -> Anabelle Porras Carrillo | G13: =B!B13 -> 2 | H13: =B!C13 -> (¿Pa' qué me estás llamando?) Dime si es verdad que él te trae loca (¿Y a vos qué te importa?) (¿Ah, sí?) Aún no lo creo, en tan poco tiempo y ya besas otra boca ¡De malas! (¿Qué?) Dime cuál fue mi error (dime) Si mi único delito solo fue amarte Hoy soy el perdedor (bebé, nomás) Y él me ha robado el truco para enamorarte (¿qué pasa, mi amor?) | I13: ='C'!A13 -> BRANDON PALACIOS DELGADO | J13: ='C'!B13 -> 2 | K13: ='C'!C13 -> (¿Pa' qué me estás llamando?) Dime si es verdad que él te trae loca (¿Y a vos qué te importa?) (¿Ah, sí?) Aún no lo creo, en tan poco tiempo y ya besas otra boca ¡De malas! (¿Qué?) Dime cuál fue mi error (dime) Si mi único delito solo fue amarte Hoy soy el perdedor (bebé, nomás) Y él me ha robado el truco para enamorarte (¿qué pasa, mi amor?) | M13: =IF(B13=0,"X"," ") | N13: 0
... A691: =IF(B691>0,"REGAETTON","BALADA") -> REGAETTON | B691: =SUM(D691,G691,J691,N691) -> 6 | C691: =A!A691 -> Arturo Daniels Fernández | D691: =A!B691 -> 2 | E691: =A!C691 -> Zúmbale mambo, pa' que mis gatas prendan los motore' Zúmbale mambo, pa' que mis gatas prendan los motore' Zúmbale mambo, pa' que mis gatas prendan los motore' Que se preparen, que lo que viene es pa' que le den (¡duro!) Mamita, yo sé que tú no te me vas a quitar (¡duro!) Lo que me gusta es que tú te dejas llevar (¡duro!) Todos los weekend, ella sale a vacilar (¡duro!) Mi gata no para de janguear, porque | F691: =B!A691 -> Leonardo Sibaja Campos | G691: =B!B691 -> 2 | H691: =B!C691 -> Zúmbale mambo, pa' que mis gatas prendan los motore' Zúmbale mambo, pa' que mis gatas prendan los motore' Zúmbale mambo, pa' que mis gatas prendan los motore' Que se preparen, que lo que viene es pa' que le den (¡duro!) Mamita, yo sé que tú no te me vas a quitar (¡duro!) Lo que me gusta es que tú te dejas llevar (¡duro!) Todos los weekend, ella sale a vacilar (¡duro!) Mi gata no para de janguear, porque | I691: ='C'!A691 -> LUIS ARIAS GÓMEZ | J691: ='C'!B691 -> 2 | K691: ='C'!C691 -> Zúmbale mambo, pa' que mis gatas prendan los motore' Zúmbale mambo, pa' que mis gatas prendan los motore' Zúmbale mambo, pa' que mis gatas prendan los motore' Que se preparen, que lo que viene es pa' que le den (¡duro!) Mamita, yo sé que tú no te me vas a quitar (¡duro!) Lo que me gusta es que tú te dejas llevar (¡duro!) Todos los weekend, ella sale a vacilar (¡duro!) Mi gata no para de janguear, porque | M691: =IF(B691=0,"X"," ") | N691: 0
B692: =COUNTIF(B1:B691,0) -> 0 | C692: =A!A692 | D692: =A!B692 | E692: =A!C692 | F692: =B!A692 | G692: =B!B692 | H692: =B!C692 | I692: ='C'!A692 | J692: ='C'!B692 | K692: ='C'!C692 | M692: =IF(B692=0,"X"," ") -> X | N692: 0
C693: =A!A693 | D693: =A!B693 | E693: =A!C693 | F693: =B!A693 | G693: =B!B693 | H693: =B!C693 | I693: ='C'!A693 | J693: ='C'!B693 | K693: ='C'!C693
C694: =A!A694 | D694: =A!B694 | E694: =A!C694 | F694: =B!A694 | G694: =B!B694 | H694: =B!C694 | I694: ='C'!A694 | J694: ='C'!B694 | K694: ='C'!C694
C695: =A!A695 | D695: =A!B695 | E695: =A!C695 | F695: =B!A695 | G695: =B!B695 | H695: =B!C695 | I695: ='C'!A695 | J695: ='C'!B695 | K695: ='C'!C695
C696: =A!A696 | D696: =A!B696 | E696: =A!C696 | F696: =B!A696 | G696: =B!B696 | H696: =B!C696 | I696: ='C'!A696 | J696: ='C'!B696 | K696: ='C'!C696

Sheet Entrenamiento
A1: =AGREEMENT!A1 -> CATEGORIA | B1: =AGREEMENT!E1 -> FRAGMENTO DE LETRAS DE CANCIONES (ALREDEDOR DE 30+ PALABRAS)
A2: =AGREEMENT!A606 -> BALADA | B2: =AGREEMENT!E606 -> Vuelve a mí Que solo y triste me quedé sin ti Y vivo sin hallar a quien querer Escúchame, mi amor Vuelve a mí Que solo y triste me quedé sin ti Y vivo sin hallar a quien querer Escúchame, mi amor
A3: =AGREEMENT!A488 -> BALADA | B3: =AGREEMENT!E488 -> Si aún no me lo crees, amor Y quieres, tú, correr el riesgo Verás que soy realmente bueno en engañar Y hacer sufrir y hacer llorar A quien más quiero, uoh-oh, uoh-oh, uoh-oh-oh
A4: =AGREEMENT!A411 -> BALADA | B4: =AGREEMENT!E411 -> Por cada beso tuyo Un sufrimiento recibí sin merecerlo No quise hacerle caso al corazón Que fue el primero en comprenderlo Ya sentí, ya comprendí que no me quieres Que seré juguete vil de tus placeres
A5: =AGREEMENT!A319 -> REGAETTON | B5: =AGREEMENT!E319 -> Mi bicho anda fugao' y yo quiero que tú me lo esconda' Agárralo como bonga Se metió una pepa que la pone cachonda Chinga en lo' Audi, no en lo' Honda Ey, si te lo meto no me llame' Que esto no es pa' que me ame', ey Si tu novio no te mama el culo Pa' eso que no mame Baja pa' casa que yo te lambo toa' Mami, yo te lambo toa' Baja pa' casa que yo te rompo toa', ey Que yo te rompo toa' Baja pa' casa que yo te lambo toa' (sigue) Mami, yo te lambo toa' (sigue) Dime, sierva (papi, sigue) Si tú fumas yerba (papi, pa-pa)
A6: =AGREEMENT!A53 -> REGAETTON | B6: =AGREEMENT!E53 -> Aquí pasamos moñas por el TSA Las putas se montan fácil como en GTA 200 cajas 'e paper que pedí en eBay En PR ya es legal, yo firmé la ley Fumando como Snoop Dogg y Wiz Kha Las gatas quieren Kush, no quieren Friska Prendí un bastón como el de la brisca
A7: =AGREEMENT!A306 -> REGAETTON | B7: =AGREEMENT!E306 -> Me gusta como a ti te cabe Si vamo' a culia hasta me habla en clave De ese tonton tengo la llave De ese planetita tengo nave Esque 'ta caliente y me llama pa' chinga'
A8: =AGREEMENT!A48 -> BALADA | B8: =AGREEMENT!E48 -> Antes que pase más Tiempo contigo amor Tengo que decir que eres el amor de mi vida Antes que te ame más Escucha por favor Déjame decir que todo te di Y no hay cómo explicar Pero, menos notar Simplemente, así lo sentí Cuando te vi (Wooh)
A9: =AGREEMENT!A353 -> BALADA | B9: =AGREEMENT!E353 -> No me platiques más Lo que debió pasar Antes de conocernos Sé que has tenido, horas felices Aún sin estar conmigo No quiero yo saber Qué pudo suceder En todos estos años Que tú has vivido con otras gentes Lejos de mi cariño
A10: =AGREEMENT!A686 -> REGAETTON | B10: =AGREEMENT!E686 -> Yo soy el cacique en tu propia aldea. Valgo más que todo lo que te rodea. No te la crea, recuerda que Curry la mete. Hasta que LeBron lo gardea. Baja pa' la cuesta. Que ando con la orquesta. Cabrón, no es la sexta. Yo nunca estoy abajo en las apuestas
A11: =AGREEMENT!A503 -> BALADA | B11: =AGREEMENT!E503 -> Si tú no vuelves. Se secarán todos los mares. Y esperaré sin ti. Tapiado al fondo de algún recuerdo. Si tú no vuelves. Mi voluntad se hará pequeña. Me quedaré aquí. Junto a mi perro, espiando horizontes. Si tú no vuelves. No quedarán más que desiertos. Y escucharé por si algún latido le queda a esta tierra
A12: =AGREEMENT!A339 -> REGAETTON | B12: =AGREEMENT!E339 -> Ni amigos, ni amantes Ni allegados, ni distantes ¿Qué eres mía y qué soy tuyo? Un fucking polvo que alimenta el orgullo ¿Quién es el que viene cuando el otro se va? Jugando a la mentira con besos de verdad
A13: =AGREEMENT!A635 -> REGAETTON | B13: =AGREEMENT!E635 -> Y si te vas, yo también me voy. No me dejes solo aquí esperando tu llamada. Ey, baby, tú eres la que manda en este bloque.
A14: =AGREEMENT!A154 -> REGAETTON | B14: =AGREEMENT!E154 -> Dos mil, loubutin los tacones
A15: =AGREEMENT!A609 -> REGAETTON | B15: =AGREEMENT!E609 -> Y a veces es Dolce, a veces Bulgari Cuando te lo quito después de los parties Las copas de vino, las libras de mari Tú estás bien suelta, yo de safari Tú mueve' el culo fenomenal Pa' yo devorarte como animal Si no te has vení'o, yo te vo' a esperar En mi cama y lo vo' a celebra
A16: =AGREEMENT!A631 -> REGAETTON | B16: =AGREEMENT!E631 -> Y que los tragos, hicieron estrago' en su cabeza. Ella con cualquiera no se besa, quiero que sepa que me interesa y no hay un día que no pare de pensar en su belleza.
A17: =AGREEMENT!A179 -> REGAETTON | B17: =AGREEMENT!E179 -> Ella no es normal Ella me lleva a la altura Chula ven chula Fuera del planeta ella es Chula ven chula Fuera del planeta ella es Chula ven chula Fuera del planeta ella es
A18: =AGREEMENT!A671 -> BALADA | B18: =AGREEMENT!E671 -> Yo no sé mañana, yo no sé mañana Si estaremos juntos, si se acaba el mundo Yo no sé si soy para ti, si serás para mí Si lleguemos a amarnos u odiarnos
A19: =AGREEMENT!A543 -> REGAETTON | B19: =AGREEMENT!E543 -> Te voy a explicar, empiezo con la A voy liberal, superar, llegar y triunfar y sin limitar y sin limitar, original rimar, improvisar, parar jamás llama a la fama, drama
A20: =AGREEMENT!A390 -> BALADA | B20: =AGREEMENT!E390 -> Para amarte Necesito una razón Y es difícil creer Que no exista una más que este amor Sobra tanto Dentro de este corazón Que a pesar de que dicen que los años son sabios Todavía se siente el dolor Porque todo el tiempo que pasé junto a ti Dejó tejido su hilo dentro de mí
A21: =AGREEMENT!A96 -> REGAETTON | B21: =AGREEMENT!E96 -> Casi siempre me llama a las 3 de la mañana Dice que soy su pana El que te quita las ganas Hemos hecho de to' Muchas posiciones en la escalera Amarrao en la cama Yo encima de ella Amanecimos en la bañera Y me la comí embarra’ de nutella
A22: =AGREEMENT!A485 -> BALADA | B22: =AGREEMENT!E485 -> Se te olvida, que me quieres a pesar de lo que dices. Pues llevamos en el alma cicatrices, imposibles de borrar, se te olvida, que hasta puedo hacerte mal si me decido. Pues tu amor lo tengo muy comprometido. Pero a fuerzas no será, y hoy resulta, que no soy de la estatura de tu vida. Y al dejarme casi, casi, se te olvida. Que hay un pacto entre los dos.
A23: =AGREEMENT!A246 -> BALADA | B23: =AGREEMENT!E246 -> Hoy le doy gracias al cielo por las veces que me equivoqué Y porque te encontré Me devolviste la fe, me presentaste a Cupido Y ahora parcho con él El brillo de los ojos se me nota Y los que me conocen saben que me curé Porque ahora ando en otra He dejado el whisky por usted
A24: =AGREEMENT!A172 -> REGAETTON | B24: =AGREEMENT!E172 -> Ella casi ni sale La traicionó el amor Tiene par de amistades Pero no quiere relación Donde va sobresale En sus ojos se ve la ilusión Pero llamó su amiga Que se olvide que esta es su canción Y baila, baila, baila Ponle música pa que esto no pare Baila, baila, baila Tengo que besarte antes que se acabe
A25: =AGREEMENT!A435 -> BALADA | B25: =AGREEMENT!E435 -> Que jamás imaginaste. Que llegaríamos hasta hoy. Que es mejor terminar todo. Para que no sufra tu amor. Lo hubieras pensado cuando me miraste. Con esa sonrisa que me hizo temblar. Y antes de decir la frase. Que me hizo sentir que yo era algo especial. Antes de que con tu suéter. Quitaras el frío de mi soledad. Antes de robarme un beso. Y encender mi cuerpo y no poder parar. No querías lastimarme. No querías lastimarme. ¡Me querías matar!
A26: =AGREEMENT!A30 -> BALADA | B26: =AGREEMENT!E30 -> Amar es cuando la proteges De la lluvia y el viento Amar es cuando tú la abrazas Y te olvidas del tiempo Amar es cuando tú la ves Y te pones nervioso Amar es cuando te das cuenta De tus sentimientos Por amarte robaría una estrella Y te la regalaría Por amarte cruzaría los mares Solo por abrazarte
A27: =AGREEMENT!A462 -> REGAETTON | B27: =AGREEMENT!E462 -> Quiero sacarte pa la calle y que pregunten to los compa' De dónde saqué esa porno star Es que con una baby así cualquiera ronca Que te presuman, no te gusta que te escondan, no Este bandido ya se retiró El que quería contigo se jodió Es que son muchas cosas juntas Y si se preguntan, ese culo lo tengo yo
A28: =AGREEMENT!A283 -> REGAETTON | B28: =AGREEMENT!E283 -> Los recuerdos de mi infancia son muy bellos fuimos pobres sin riquezas ni dinero pero a dios cada mañana le agradezco que por madre me mando un ángel del cielo.
A29: =AGREEMENT!A168 -> BALADA | B29: =AGREEMENT!E168 -> Él me mintió, él me mintió. Era un juego y nada más. Era solo un juego cruel de su vanidad. Él me mintió. Con el corazón destrozado Y el rostro mojado. Soy tan desdichada, quisiera morirme. Mentiras, todo era mentira. Palabras al viento. Tan solo un capricho que el niño tenía
A30: =AGREEMENT!A70 -> REGAETTON | B30: =AGREEMENT!E70 -> Ayer me besaste y no podías parar Y me bailaste hasta el amanecer Cuando desperté yo te quise llamar Y ahora me dice que borró cassete Que no se acuerda de esa noche Porque ella borró cassette Dice que no me conoce Y quiero volverla ver
A31: =AGREEMENT!A210 -> BALADA | B31: =AGREEMENT!E210 -> Esta historia terminó, no existe Lo que un día construimos, se ha esfumado Pareciera que es más fácil dejarnos Pero eres un fantasma conmigo caminando
A32: =AGREEMENT!A247 -> BALADA | B32: =AGREEMENT!E247 -> Hoy mi playa se viste de amargura, oh Porque tu barca tiene que partir A cruzar otros mares de locura Cuida que no naufrague en tu vivir Cuando la luz del sol se esté apagando y Te sientas cansada de vagar Piensa que yo por ti estaré esperando Hasta que tú decidas regresar
A33: =AGREEMENT!A236 -> BALADA | B33: =AGREEMENT!E236 -> Hasta que me olvides, voy a intentarlo No habrá quién me seque tus labios por dentro y por fuera No habrá quién desnude mi nombre una tarde cualquiera Hasta que me olvides tanto que No exista mañana ni después, no, no Hasta que me olvides, voy a intentarlo No habrá quién desnude mi boca como tu sonrisa Y voy a rodar como lágrima entre la llovizna Hasta que me olvides tanto que No exista mañana ni después
A34: =AGREEMENT!A610 -> REGAETTON | B34: =AGREEMENT!E610 -> Y a veces es Dolce, a veces Bulgari Cuando te lo quito después de los parties Las copas de vino, las libras de mari Tú estás bien suelta, yo de safari Tú mueve' el culo fenomenal Pa' yo devorarte como animal Si no te has vení'o, yo te vo'a esperar En mi cama y lo vo' a celebrar
A35: =AGREEMENT!A537 -> BALADA | B35: =AGREEMENT!E537 -> Te hiciste indispensable para mí, y, y Y con los ojos cerrados te seguí Si yo busqué dolor, lo conseguí No eres la persona que pensé Que creí, que pedí
A36: =AGREEMENT!A292 -> BALADA | B36: =AGREEMENT!E292 -> Me abrazaría al diablo sin dudar Por ver tu cara al escucharme hablar Eres todo lo que más quiero Pero te pierdo en mis silencios Mis ojos son dos cruces negras
A37: =AGREEMENT!A140 -> REGAETTON | B37: =AGREEMENT!E140 -> Dembow y reggaeton, mami, llégale a la mezcla y dale pa'l hotel, trae una amiga extra pónteme fresca como Carmen Electra y yo les doy corriente de la forma correcta
A38: =AGREEMENT!A176 -> BALADA | B38: =AGREEMENT!E176 -> Ella es un escándalo Ella te quita el oxígeno Es una obra de arte, ella es punto y aparte Ella es feliz con lo básico Y si la vieras bailando Lento, es un espectáculo Cómo piensa es brillante, ella es impresionante Todo en ella es romántico
A39: =AGREEMENT!A144 -> BALADA | B39: =AGREEMENT!E144 -> Después correr felices cara al viento, caernos en la arena, ya sin aliento. y tú en un suspiro tú, en cada pensamiento tú. Y yo yo me callaba yo, por no arruinarlo todo yo. Y besarte la boca, robarte la boca.
A40: =AGREEMENT!A458 -> BALADA | B40: =AGREEMENT!E458 -> QueridaCada momento de mi vidaYo pienso en ti más cada díaMira mi soledad, mira mi soledadQue no me sienta nada bien, oh ven yaQueridaNo me ha sanado bien la heridaTe extraño y lloro todavíaMira mi soledad, mira mi soledadQue no me sienta nada bien, oh ven yaQueridaPiensa en mi sólo un momento y venDate cuenta de que el tiempo es cruelY lo he pasado yo sin ti, oh ven ya
A41: =AGREEMENT!A131 -> BALADA | B41: =AGREEMENT!E131 -> De mirarte a los ojos, sé cómo te siente' Extraño la sonrisa reluciente de siempre Todo pasa, sé paciente, habrá tiempo suficiente Pa' sanar las herida' y borrar lo negativo de la mente Sabes que yo, así, no puedo verte
A42: =AGREEMENT!A538 -> BALADA | B42: =AGREEMENT!E538 -> Te juro que te pienso Hago el mejor intento El tiempo pasa lento Y yo me voy muriendo (y yo me voy muriendo) Si llega la noche y tú no contestas Te juro me quedo esperando a tu puerta Vivo pasando las noches en vela Y sigo cantando bajo la luna llena Súbeme la radio que esta es mi canción Siente el bajo que va subiendo Tráeme el alcohol que quita el dolor Hoy vamos a juntar la luna y el sol
A43: =AGREEMENT!A420 -> BALADA | B43: =AGREEMENT!E420 -> Porque al sentir tu presencia todo es tan hermoso porque al sentirte tan cerca me siento dichoso será ese deseo tan grande de verte a mi lado que me hace sentir que estoy enamorado
A44: =AGREEMENT!A20 -> BALADA | B44: =AGREEMENT!E20 -> Abrázame y dime que me amas
A45: =AGREEMENT!A72 -> REGAETTON | B45: =AGREEMENT!E72 -> Ayer te vi bonita (bonita) caminando por la playa Sola y desorientada, ma' ¿Por qué te encuentras solita (sola)? Tú mereces ser amada, querida, y yo maltratado, ma'
A46: =AGREEMENT!A491 -> REGAETTON | B46: =AGREEMENT!E491 -> Si están celoso' de que te tengo, pero yo no (ey, yo no) Basta de esto, solo entremo' en la habitación (la habitación) Apaga la' luce' y empecemo' con la narración Romeo y Julieta, pero con má' piquete y má' flow, ey
A47: =AGREEMENT!A298 -> BALADA | B47: =AGREEMENT!E298 -> Me dediqué a perderte Y me ausenté en momentos que se han ido para siempre Me dediqué a no verte Y me encerré en mi mundo y no pudiste detenerme Y me alejé mil veces Y cuando regresé te había perdido para siempre Y quise detenerte
A48: =AGREEMENT!A14 -> REGAETTON | B48: =AGREEMENT!E14 -> A ella le gusta la gasolina (¡Dame más gasolina!) Cómo le encanta la gasolina (¡Dame más gasolina!) Ella prende las turbinas, no discrimina No se pierde ni un party de marquesina Se acicala hasta pa' la esquina Luce tan bien que hasta la sombra le combina
A49: =AGREEMENT!A561 -> REGAETTON | B49: =AGREEMENT!E561 -> Tu ere’ bien puta Es lo que ella buscaz se difraza y me ejecuta cuando se convierte en puta Que le haga un palde Willy -¿WTF?- y se lo enjuague por su ruta Ella sabe con cojones pero se hace la bruta
A50: =AGREEMENT!A188 -> BALADA | B50: =AGREEMENT!E188 -> En mi cara sentada sigo detrás de tu alma persiguiendo recuerdos recuerdos que me abrazan siempre que tengo miedo te llevaste lo que me hacía sentir vivo
A51: =AGREEMENT!A380 -> BALADA | B51: =AGREEMENT!E380 -> Oh, qué será, qué será Que anda suspirando por las alcobas Que anda susurrando versos de trova Que anda escondiendo bajo las ropas Que anda en las cabezas, anda en las bocas Que va encendiendo velas en los callejones Que están hablando alto en los bodegones Gritando en el mercado, las voces esas Es la naturaleza, será, que será Que no tiene certeza y nunca te da Lo que no tiene arreglo, y nunca tendrá Que no tiene tamaño
A52: =AGREEMENT!A59 -> REGAETTON | B52: =AGREEMENT!E59 -> Atrévete-te-te, salte del closet Destápate, quítate el esmalte Deja de taparte, que nadie va a retratarte Levántate, ponte hyper Préndete, sácale chispa al starter Préndete en fuego como un lighter Sacúdete el sudor, como si fueras un wiper Que tú ere' callejera, Street Fighter
A53: =AGREEMENT!A674 -> REGAETTON | B53: =AGREEMENT!E674 -> Yo parezco una correa porque doy fuetazo' Las gente' me dicen: Alfa, balbara-sa-sa-zo Yo soy un Jordan, tú viene' siendo Puma Tiene' que quitarte, llegó el toro con tutuma
A54: =AGREEMENT!A418 -> BALADA | B54: =AGREEMENT!E418 -> Por la culpa de una interesada Dejé una interesante Ay, qué mal, pequé por ignorante Cambié una de verdad por un maniquí Por su brillo me dejé llevar Pensé que era un diamante, pero no Resultó ser farsante Y no fue solo tiempo lo que le invertí Porque hay amores que matan a punta de besos Y amores que engañan por un par de pesos Tarde lo entendí Y me arrepentí Cambié oro por plata, tú eras mi universo Y ella solo una estrella, y me estrellé por eso Qué estúpido fui Lo que me perdí Cambié una interesante por una interesada, y por eso No se deja la del proceso
A55: =AGREEMENT!A3 -> REGAETTON | B55: =AGREEMENT!E3 -> ¿Cómo te llamas, baby? Desde que te vi supe que eras pa’ mí Dile a tus amigas que andamo' ready Esto lo seguimo' en el after party
A56: =AGREEMENT!A278 -> REGAETTON | B56: =AGREEMENT!E278 -> Lo de nosotros es algo de novelas La tipa nunca me cela Me gusta verte con poca tela Todo lo que queda, quítese esa franela Como música, yo la compongo Ella baila al ritmo que yo pongo Como Kalimba, estoy tocando fondo Y siempre me la como en plato hondo
A57: =AGREEMENT!A312 -> BALADA | B57: =AGREEMENT!E312 -> Me queda un por ciento Y lo usaré solo para decirte lo mucho que lo siento Que, si me ven con otra en una disco, solo es perdiendo el tiempo Baby, ¿pa qué te miento? Eso de que me vieron feliz, no, no es cierto
A58: =AGREEMENT!A584 -> BALADA | B58: =AGREEMENT!E584 -> Tú, la misma de ayer, la incondicional. La que no espera nada. Tú, la misma de ayer, la que no supo odiar. No sé por qué te fuiste.
A59: =AGREEMENT!A663 -> BALADA | B59: =AGREEMENT!E663 -> Ya sé que no hubo nadie que te diera lo que yo te di Que nadie te ha cuidado como te cuidé Por eso comprendo que estás aquí Pero ha pasado el tiempo y yo también cambié Si no supiste amar Ahora te puedes marchar
A60: =AGREEMENT!A78 -> REGAETTON | B60: =AGREEMENT!E78 -> Baby, la nota ya está haciendo efecto. Mi mundo está jodío' y me siento perfecto. Porque estás tú, aquí, moviéndote así, no pare'. Baby, tú eres mi droga, esta noche no le baje'. Porque la nota ya está haciendo efecto
A61: =AGREEMENT!A191 -> BALADA | B61: =AGREEMENT!E191 -> Entra en mi vida, te abro la puerta Sé que en tus brazos ya no habrá noches desiertas Entra en mi vida, yo te lo ruego Te comencé por extrañar, pero empecé a necesitarte luego
A62: =AGREEMENT!A261 -> BALADA | B62: =AGREEMENT!E261 -> La luz ya No alcanza No quieras caminar sobre el dolor Descalza Un ángel Te cuida Y puso en mi boca la verdad para mostrarte la salida
A63: =AGREEMENT!A94 -> BALADA | B63: =AGREEMENT!E94 -> Cada camino que piso, me lleva hacia el Ninguno de mis cinco sentidos, te olvida después Entre las cosas que hago, y las que digo Va siempre conmigo, es mi sombra fiel No es ningun juego de niños, estar como estoy No como, no duermo, no vivo, pensando en su amor Siempre crei que los celos, eran un cuento Y son el infierno, que arde sin control
A64: =AGREEMENT!A374 -> BALADA | B64: =AGREEMENT!E374 -> Nuestro amor sabe a chocolate Un corazón de bombón que late Nuestro amor sabe a chocolate Oh oh oh oh oh Quien no ha probado y no mas Verás que te hace volar El cielo en tu paladar Así me quiero quedar Verás que te hace volar El cielo en tu paladar Así me quiero quedar, contigo
A65: =AGREEMENT!A574 -> REGAETTON | B65: =AGREEMENT!E574 -> Tú puedes coger con otro, siempre y cuando no te catch Da-da-dame chance de lamerte el hoyo dilatado Ya sabes que te lo embarro de lado, trr Ya sabes que te cojo vestido de diputado Ya sabes que al chile, me sobra varo Trr, trr, trr, martillazo en el ano
A66: =AGREEMENT!A37 -> BALADA | B66: =AGREEMENT!E37 -> Amor como el nuestro no hay dos en la vida Por más que se busque, por más que se esconda Tú duermes conmigo toditas las noches Te quedas callada, sin ningún reproche Por eso te quiero, por eso te adoro Tú eres en mi vida, todo mi tesoro A veces regreso, borracho de angustia Te lleno de besos y caricias mustias Pero estás dormida, no sientes caricias Te abrazo a mi pecho, me duermo contigo
A67: =AGREEMENT!A170 -> REGAETTON | B67: =AGREEMENT!E170 -> El protocolo como foco me equivoco, choco un coco me sofoco poco a poco me controlo y yo solo llego y lo toco fumo y enrollo llegando a la lu
A68: =AGREEMENT!A560 -> BALADA | B68: =AGREEMENT!E560 -> Tú de qué vas, llenando mi vida de tantas cosas buenas. De pronto me dictas lo que hay que hacer. Me llevas de la mano a conocer. Un mundo nuevo.
A69: =AGREEMENT!A513 -> BALADA | B69: =AGREEMENT!E513 -> Siento el dolor que tu causas en mí Me haces llorar, no quiero ver el fin Esta canción la canto para ti Solo escucha y déjate sentir Hoy nuestro tiempo está por acabar Y ya nunca va haber otra ola igual Cada momento que vimos pasar Sabes que nunca me vas a olvidar
A70: =AGREEMENT!A515 -> REGAETTON | B70: =AGREEMENT!E515 -> Sin ser cara y lindo, en la cama causo sismos. Mantengo mi ritmo, les doy satisfacción.Adoro ver sus cuerpos empapados en sudor. Un extra de pasión y diversas posiciones. Han hecho que las grupies coleccionen mis condones. No te asombres, esto es real, no es ninguna fantasía. Mami, no estés triste, soy tu papi todavía. Soy tu vida, soy tu muerte y vivo para cogerte. Tengo frío el corazón, pero la verga caliente
A71: =AGREEMENT!A33 -> REGAETTON | B71: =AGREEMENT!E33 -> Amiga mía, lo sé, solo vives por él, que lo sabe también. Pero él no te ve como yo, suplicarle a mi boca. Que diga que me ha confesado entre copas. Que es con tu piel con quien sueña de noche
A72: =AGREEMENT!A605 -> BALADA | B72: =AGREEMENT!E605 -> Voy De nuevo recordando lo que soy Sabiendo lo que das y lo que doy En mí no queda espacio para ti, y, y Y, y el tiempo hizo lo suyo y comprendí Las cosas no suceden porque sí No eres la persona que pensé Que creí, que pedí
A73: =AGREEMENT!A93 -> BALADA | B73: =AGREEMENT!E93 -> Buenas noches, mucho gusto, eras una chica más Después de cinco minutos ya eras alguien especial Sin hablarme, sin tocarme, algo dentro se encendió En tus ojos se hacía tarde y me olvidaba del reloj
A74: =AGREEMENT!A234 -> BALADA | B74: =AGREEMENT!E234 -> Hasta que me olvides Voy a amarte tanto, tanto Como fuego entre tus brazos Hasta que me olvides Hasta que me olvides Y me rompa en mil pedazos Continuar mi gran teatro Hasta que me olvides, hasta que me olvides
A75: =AGREEMENT!A460 -> BALADA | B75: =AGREEMENT!E460 -> Quiero dormir cansado Para no pensar en ti Quiero dormir profundamente Y no despertar llorando Con la pena de no verte
A76: =AGREEMENT!A531 -> REGAETTON | B76: =AGREEMENT!E531 -> Te escribo mensajes todas las noches pero los borro pa'quedar en visto ese mal rato mejor me lo ahorro mi orgullo es tan grande y abajo me pesan no pienso humillarme
A77: =AGREEMENT!A443 -> REGAETTON | B77: =AGREEMENT!E443 -> Que te haré subir al cielo Bajar y besar el mismo horas infierno Yo que será tu dolor eterno Tú tan caliente, yo tan invierno Tú que fuiste presa tan fácil lloras Tú tan libre, ahora vivo yo en tus Hay algo en ti de mí que te azora Que tus sueños controla y te descontrola
A78: =AGREEMENT!A558 -> BALADA | B78: =AGREEMENT!E558 -> Traigo en los bolsillos tanta soledad. Desde que te fuiste no me queda más. Que una foto gris y un triste sentimiento. Lo que más lastima es tanta confusión. En cada resquicio de mi corazón ¿Cómo hacerte a un lado de mis pensamientos? (por ti)
A79: =AGREEMENT!A550 -> BALADA | B79: =AGREEMENT!E550 -> Tengo una flor de bolsillo. Marchita de buscar a una mujer que me quiera. Y reciba su perfume hasta traer la primavera. Y me enseñe lo que no aprendí de la vida. Que brilla más cada día
A80: =AGREEMENT!A6 -> REGAETTON | B80: =AGREEMENT!E6 -> ¿Por qué sigues con él? (¿Por qué sigues con él?) Si borracha me confesaste que él no te lo hace bien Tú le calientas la comida, pero él no te sabe comer (okay) Si pruebas, no vas a volver (no), no, yeh
A81: =AGREEMENT!A453 -> REGAETTON | B81: =AGREEMENT!E453 -> Que va a explotar como fiesta patronal Que va a explotar como palestino Yo sé que a ti te gusta el pop-rock latino Pero es que el reggaetón se te mete por los intestino' Por debajo de la falda, como un submarino Y te saca lo de indio taíno Ya tú sabe', en taparrabo, mamá En el nombre de Agüeybaná, no hay más na' Para na' que yo te vo'a mentir Yo sé que yo también quiero consumir de tu perejil
A82: =AGREEMENT!A417 -> BALADA | B82: =AGREEMENT!E417 -> Por favor que alguien me diga Qué se toma pa' las penas Cuando está recién herido Y el alcohol no ayuda pa' olvidarme de ella Pa' olvidarme de ella Ya bailé con otros labios Y me acuerdo siempre de ella He cantado mil rancheras Y el alcohol no ayuda pa' olvidarme de ella Pa' olvidarme de ella Que descanse en paz aquí Tú te fuiste y yo me fui Mi cuerpo camina solo Mi alma se fue tras de ti Tú no tienes la culpa Que yo no me acostumbro a estar sin ti (Yo no me acostumbro a estar sin ti)
A83: =AGREEMENT!A32 -> BALADA | B83: =AGREEMENT!E32 -> Amiga mía, lo sé, solo vives por él, que lo sabe también Pero él no te ve como yo, suplicarle a mi boca Que diga que me ha confesado entre copas Que es con tu piel con quien sueña de noche Y que enloquece con cada botón Que te desabrochas pensando en sus manos Él no te ha visto temblar, esperando Una palabra, algún gesto, un abrazo
A84: =AGREEMENT!A691 -> REGAETTON | B84: =AGREEMENT!E691 -> Zúmbale mambo, pa' que mis gatas prendan los motore' Zúmbale mambo, pa' que mis gatas prendan los motore' Zúmbale mambo, pa' que mis gatas prendan los motore' Que se preparen, que lo que viene es pa' que le den (¡duro!) Mamita, yo sé que tú no te me vas a quitar (¡duro!) Lo que me gusta es que tú te dejas llevar (¡duro!) Todos los weekend, ella sale a vacilar (¡duro!) Mi gata no para de janguear, porque
A85: =AGREEMENT!A91 -> REGAETTON | B85: =AGREEMENT!E91 -> Blanquita, te dejo canela cuando te someto a mi lujureo Es de la isla, su encanto lo aventureo Lo jalo con nuestro' video', ya ni las porno googleo, no No veo un culo que me guste más cabrón por más Reels que swipeo Y lo que me corre más es que me da esa chapa sin chapeo
A86: =AGREEMENT!A47 -> BALADA | B86: =AGREEMENT!E47 -> Antes De que el mundo se formara Y que el pájaro cantara Ya te esperaba Antes Del perfume de las rosas Y de tantas tantas cosas Ya te esperaba
A87: =AGREEMENT!A664 -> BALADA | B87: =AGREEMENT!E664 -> Ya te encontré varios rasguños. Que te hicieron por ahí. Pero mi loco amor. Es tu mejor doctor. Voy a curarte el alma en duelo. Voy a dejarte como nuevo. Y todo va a pasar. Pronto verás el sol brillar. Tú más que nadie mereces ser feliz.Ya vas a ver cómo van sanando. Poco a poco tus heridas. Ya vas a ver cómo va. La misma vida a decantar la sal que sobra en el mar
A88: =AGREEMENT!A166 -> BALADA | B88: =AGREEMENT!E166 -> Él me mintió Él me dijo que me amaba Y no era verdad, él me mintió No me amaba, nunca me amó Él dejó que lo adorara Él me mintió, él me mintió Era un juego y nada más Era solo un juego cruel de su vanidad Él me mintió
A89: =AGREEMENT!A184 -> REGAETTON | B89: =AGREEMENT!E184 -> Ella viene por ahí y nunca llega sola Ella nunca llega sola To' los bandi-di- se sueltan las pistola' Esta noche lo que hay (dice) Perreo, baby, sobeteo, baby Tra-tra, baby, hasta abajo, baby En la disco, baby, yo te cojo, baby Tra-tra, baby, tra-tra, baby
A90: =AGREEMENT!A238 -> REGAETTON | B90: =AGREEMENT!E238 -> Hay un hombre moribundo aquí Dime, ¿quién lo puede revivir? Hay un hombre moribundo aquí Dime, ¿quién lo puede revivir? Tú tienes la receta La fórmula secreta Para poner en ritmo en mi corazón No existe medicina Doctores, ni aspirina Para el dolor que siente mi corazón Casi no siento mis pálpitos Al rescate que venga la paramédico Necesito que me des un electroshock Eh-eh, de tu calor
A91: =AGREEMENT!A103 -> BALADA | B91: =AGREEMENT!E103 -> Como me apena el verte llorar Toma mi mano, siéntela Yo te protejo de cualquier cosa No llores más, aquí estoy Frágil te ves, dulce y sensual Quiero abrazarte y te protegeré Esta fusión es irrompible No llores más, aquí estoy
A92: =AGREEMENT!A13 -> REGAETTON | B92: =AGREEMENT!E13 -> (¿Pa' qué me estás llamando?) Dime si es verdad que él te trae loca (¿Y a vos qué te importa?) (¿Ah, sí?) Aún no lo creo, en tan poco tiempo y ya besas otra boca ¡De malas! (¿Qué?) Dime cuál fue mi error (dime) Si mi único delito solo fue amarte Hoy soy el perdedor (bebé, nomás) Y él me ha robado el truco para enamorarte (¿qué pasa, mi amor?)
A93: =AGREEMENT!A324 -> REGAETTON | B93: =AGREEMENT!E324 -> Mi mujer me estaba llamando Pero yo no contesté (uah, baby, sube) Porque yo estaba contigo perreando Y de ella me olvidé (mami) Dio' mío, perdóname No sé por qué yo le fallé (fallé, uah) Yo estaba en la disco perreando Y con ella me enredé (uah) Yo estaba en la disco perreando (oh, oh) Yo estaba en la disco perreando (eh, eh, eh, uah) Yo estaba en la disco perreando (uah, uah) Yo estaba en la disco perreando
A94: =AGREEMENT!A266 -> REGAETTON | B94: =AGREEMENT!E266 -> La mano arriba, cintura sola Da media vuelta, danza kuduro No te canse' ahora, que esto solo empieza Mueve la cabeza, danza kuduro Quién puede domar la fuerza del mal Que se mete por tu' vena' (¡Don!) Lo caliente del Sol que se te metió Y no te deja quieta, nena (¡toma, toma!) Quién puede parar eso que al bailar Descontrola tu' cadera' (sexy) Y ese fuego que quema por dentro y lento Te convierte en fiera
A95: =AGREEMENT!A576 -> REGAETTON | B95: =AGREEMENT!E576 -> Tú sabe' cómo soy, bebé, yo casi no jangueo. Y ahora salgo to' los día pa' ver si te veo. Aunque sea de lejito', con la hookah y el perreo. Mañana voy a terapia, hoy voy pa'l teteo. Otro mensaje que escribo y no envío. Pero por si acaso lo guardo en mis nota'
A96: =AGREEMENT!A235 -> BALADA | B96: =AGREEMENT!E235 -> Hasta que me olvides, voy a intentarlo No habrá quién me seque tus labios por dentro y por fuera No habrá quién desnude mi nombre una tarde cualquiera Hasta que me olvides tanto que No exista mañana ni después, no, no
A97: =AGREEMENT!A623 -> REGAETTON | B97: =AGREEMENT!E623 -> Y me dices: "Cuidado, no puedes entenderlo" Me perdonas la vida, me llevas al infierno Y me pides la llave del portal de los sueño' Que me corten las manos si la tengo yo Y yo sigo en mi pelea conmigo (oh) No estoy sordo, simplemente es que no atino Como un lienzo en el Museo del Prado (ey) Pasa el tiempo y nos quedamos a cuadro' Y tú sigues esperando respuesta' Y no existe la pregunta correcta
A98: =AGREEMENT!A638 -> BALADA | B98: =AGREEMENT!E638 -> Y solo ten mi número telefónico para cuando te sientas sola. Y me llamas a mí, recuerda que yo estaré para ti a todas horas. Y solo ten mi número telefónico.
A99: =AGREEMENT!A134 -> BALADA | B99: =AGREEMENT!E134 -> Debo interpretar tus gritos Tus llamadas, tus caricias entre cortadas Y tus arranques de pasión Debo buscar dentro de tanto desperfecto La moraleja de este cuento Debo domar tu corazón
A100: =AGREEMENT!A252 -> REGAETTON | B100: =AGREEMENT!E252 -> Hula hoop Hula, hula hoop Hula, hula hoop Hula cintura dura, dura Hula hoop Hula, hula hoop Hula, hula hoop Hula, cintura y nos fuimos Hula hoop Hula, hula hoop Hula, hula hoop Hula, cintura dura, dura Hula hoop Hula, hula hoop Hula, hula hoop Hula cintura dura, dura
...

Sheet Testing
A1: =AGREEMENT!A1 -> CATEGORIA | B1: =AGREEMENT!E1 -> FRAGMENTO DE LETRAS DE CANCIONES (ALREDEDOR DE 30+ PALABRAS)
A2: =AGREEMENT!A114 -> BALADA | B2: =AGREEMENT!E114 -> Cuando me enamoro A veces, desespero Cuando me enamoro Y cuando menos me lo espero, me enamoro Se detiene el tiempo Me viene el alma al cuerpo Sonrío Cuando me enamoro
A3: =AGREEMENT!A43 -> BALADA | B3: =AGREEMENT!E43 -> Ana, Ana mía mi pasión y mi poesía en mis besos tus deseos ardía Ana es una extraña melodía la razón de mi alegría. Ana, Ana mía realidad y fantasía.
A4: =AGREEMENT!A301 -> REGAETTON | B4: =AGREEMENT!E301 -> Me dices que pa' qué y yo te digo que si no somos nada, ¿entonces a qué estamos jugando? El tiempo volando y tú sin mí no sé si bien la estás pasando.
A5: =AGREEMENT!A672 -> REGAETTON | B5: =AGREEMENT!E672 -> Yo no soy y ni voy a ser tu bizcochito Pero tengo to' lo que tiene delito Que me pongan en el sol, que me derrito El mal de ojo' que me manden me lo quito
A6: =AGREEMENT!A187 -> REGAETTON | B6: =AGREEMENT!E187 -> En la secundaria me doblaba la faldita. Soy una coqueta desde que era chamaquita. El del punto dice que parezco muñequita. Si me guiña el ojo, sé que quiere mi cosita. Por andar de lela reprobé un año de escuela. Yo lo que he escuchado es que le cago a la maestra. En primero me gustaba el novio de Pamela. Y lo suspendieron por caldearme en la escalera
A7: =AGREEMENT!A327 -> BALADA | B7: =AGREEMENT!E327 -> Mientes tan bien Que me sabe a verdad Todo lo que me das Ya te estoy amando Mientes tan bien Que he llegado a imaginar Que en mi amor llenas tu piel Y, aunque todo es de papel. uh-uh Mientes tan bien
A8: =AGREEMENT!A87 -> REGAETTON | B8: =AGREEMENT!E87 -> Bebecita, estás más rica que ayer (rica que ayer) Qué bueno fue volverte a ver (volverte a ver) Se ve que no te sabe querer (-er) Conmigo te ve' mejor que con él
A9: =AGREEMENT!A615 -> REGAETTON | B9: =AGREEMENT!E615 -> Y de pensar que yo contigo quiero estar Quiero probar algo de ti pa' no olvidar Yo no me sé ni su nombre (pero la quiero) Pasó y dejó su fragancia (y hasta me desesperó) Rapa-pa-pai, rapa-pa-pai (oh, oh, oh) Y rapa-pa-pai, rapa-pa-pai Así es que la quiero-quiero Rapa-pa-pai, rapa-pa-pai (oh, oh) Y rapa-pa-pai, rapa-pa-pai Así es que la quiero-quiero
A10: =AGREEMENT!A5 -> REGAETTON | B10: =AGREEMENT!E5 -> ¿Pa' qué buscar en la calle lo que abunda en mi casa? Una mamacita buena gente, qué chimba de cuerpo y de cara. Y aunque la baby es inocente y con otras se compara. Diosito la hizo humilde, pero yo la veo bien cara
A11: =AGREEMENT!A416 -> BALADA | B11: =AGREEMENT!E416 -> Por eso vete, olvida mi nombre, mi cara, mi casa Y pega la vuelta Jamás te pude comprender Vete, olvida mis ojos, mis manos, mis labios Que no te desean Estás mintiendo ya lo sé Vete, olvida que existo, que me conociste, Y no te sorprendas, olvida de todo que tú para eso Tienes experiencia
A12: =AGREEMENT!A350 -> REGAETTON | B12: =AGREEMENT!E350 -> No me importa lo que de mí se diga Viva usted su vida, que yo vivo la mía Que solo es una, disfruta el momento Que el tiempo se acaba y pa'trás no vira Bebiendo, fumando y jodiendo Sigo vacilando de party to' los día' Síguelo, oh-oh-oh, oh-oh-oh, oh-oh (Farru) Síguelo, oh-oh-oh, oh-oh-oh, oh-oh (la rola y pepa) Pepa y agua pa' la seca To' el mundo en pastilla' en la discoteca Pepa y agua pa' la seca To' el mundo en pastilla' en la discoteca
A13: =AGREEMENT!A36 -> BALADA | B13: =AGREEMENT!E36 -> Amor Si alguna vez nos vemos por ahí Invítame a un café y hazme el amor Y si ya no vuelvo a verte, ojalá que tengas suerte Ya lo ves La vida es así Tú te vas Y yo me quedo aquí
A14: =AGREEMENT!A389 -> REGAETTON | B14: =AGREEMENT!E389 -> Pa' ti naki, chicken teriyaki Tu gata quiere maki, mi gata en Kawasaki Quiero una cadena que me arruine to'a la cuenta Como Naomi en los 90 Rosa' sin tarjeta Se las mando a tu gata (ey) Te la tengo con Roleta (ey) No hizo falta serenata Pa' ti naki, chicken teriyaki Pa' ti naki, chicken teriyaki Pa' ti naki, chicken teriyaki Tu gata quiere maki (mi gata en Kawasaki) Quiero una cadena que me arruine to'a la cuenta Como Julio en los 70 (pa' ti naki, chicken teriyaki)
A15: =AGREEMENT!A25 -> BALADA | B15: =AGREEMENT!E25 -> Aléjate de mí y hazlo pronto, antes de que te mienta Tu cielo se hace gris, yo ya camino bajo la tormenta Aléjate de mí, escapa, vete, ya no debo verte Entiende que aunque pida que te vayas, no quiero perderte
A16: =AGREEMENT!A225 -> REGAETTON | B16: =AGREEMENT!E225 -> fumo y enrollo llegando a la lu ahora cierro y termino con la U mi juventud me la gozo con actitud orgulloso de mi talento y de toda mi virtud
A17: =AGREEMENT!A174 -> BALADA | B17: =AGREEMENT!E174 -> Ella es ese sueño Que tuve despierto Un recuerdo leve De esto que siento Una sacudida A mis salidas La cima de un beso en un brinco suicida Su fuente de energía Cautiva mis sensores Pues no hay que la controle Cuando baila encendía
A18: =AGREEMENT!A132 -> REGAETTON | B18: =AGREEMENT!E132 -> De mirarte a los ojos, sé cómo te siente'. Extraño la sonrisa reluciente de siempre. Todo pasa, sé paciente, habrá tiempo suficiente. Pa' sanar las herida' y borrar lo negativo de la mente. Sabes que yo, así, no puedo verte
A19: =AGREEMENT!A601 -> BALADA | B19: =AGREEMENT!E601 -> Voy a darte una segunda oportunidad. Quiero confesarte que yo nunca te dejé de amar. De mi parte, de seguro no te voy a fallar. No te pagaré con la misma moneda, yo sí sé amar.
A20: =AGREEMENT!A97 -> BALADA | B20: =AGREEMENT!E97 -> Casi todos sabemos querer Pero pocos sabemos amar Es que amar y querer no es igual Amar es sufrir querer es gozar El que ama pretende servir El que ama su vida la da Y el que quiere pretende vivir Y nunca sufrir, y nunca sufrir
A21: =AGREEMENT!A533 -> BALADA | B21: =AGREEMENT!E533 -> Te esperé, llegué a sentir que me moría Te esperé, como la luna espera el día Lo intenté, pero continuó la vida Te esperé, pero el tiempo cerró la herida
A22: =AGREEMENT!A562 -> BALADA | B22: =AGREEMENT!E562 -> Tú eres la mujer que yo he esperado tantoLa que comparte su risa y su llanto La que se entrega en alma y cuerpo La que puede darme un amor eterno Ohhh ohhh ohhh un amor eterno Por ti volvieron los colores Por ti escribo canciones Por ti aun me queda fe Por ti puedo decir que creo en el amor Solo por ti
A23: =AGREEMENT!A286 -> REGAETTON | B23: =AGREEMENT!E286 -> Mami, eres lo que quiero Cuando veo tu sonrisa Y es lo que me debilita Quiero llevarte a una cita Yo te quiero enseñar todo El amor que yo te tengo Tan sencilla que tú eres Para mí tú eres perfecta Yo te quiero amar, te quiero enseñar El amor y más Y eres perfecta Tu cuerpo hermoso que luce tan bello Y esos ojitos Ni se diga más Ni se diga más ¡Ahí te va, chiquitita!
A24: =AGREEMENT!A28 -> BALADA | B24: =AGREEMENT!E28 -> Amada mía Después de tantos años Después de tantas noches compartidas Después de tantos sueños Soñados cada día Te sigo amando tanto Amada mía Tus ojos negros Se clavan como siempre Tu beso es una llama que aún me quema Yo sigo siendo el árbol Y tú, la tierra mía Te sigo amando tanto Amada mía Amada mía Después de tantas horas De camino Tú sigues siendo playa
A25: =AGREEMENT!A9 -> REGAETTON | B25: =AGREEMENT!E9 -> ¿Qué me hizo usted? Que la quiero volver a ver Y volverla a besar Yo te paso a buscar, buscar Es que la bellaquera contigo Con nadie más la consigo De tus grito' hoy no me olvido Te-te-tengo reservao' el hotel
A26: =AGREEMENT!A45 -> BALADA | B26: =AGREEMENT!E45 -> Ansiedad, de tenerte en mis brazos, Musitando palabra de amor. Ansiedad, de tener tus encantos, Y en la boca volveré a besar........ Ansiedad, de tenerte en los brazos, musitando palabra de amor, Ansiedad de tener los encantos, Y en la boca volveré a besar. Tal vez estaré llorando mis pensamientos, Mis lágrimas son perlas que al caer al mar, Y el eco adormecido, de ese lamento
A27: =AGREEMENT!A597 -> REGAETTON | B27: =AGREEMENT!E597 -> Víveme sin miedo ahora Que sea una vida o sea una hora No me dejes libre aquí desnudo Mi nuevo espacio que ahora es tuyo, te ruego
A28: =AGREEMENT!A196 -> BALADA | B28: =AGREEMENT!E196 -> Es preciso decir que no Cuando se tiene el alma herida Porque el amor de los dos El que una vez fue el mejor hoy me lastima
A29: =AGREEMENT!A604 -> REGAETTON | B29: =AGREEMENT!E604 -> Voy buscando una lady Como tú, la quiero así Quiero que te enamores Como estoy yo de ti A casa, enviarte flores Y en tu nombre escribir Mil canciones de amores Pa' que pienses en mí Como yo pienso en ti
A30: =AGREEMENT!A229 -> REGAETTON | B30: =AGREEMENT!E229 -> Hace mucho tiempo que te quiero ver Busco la manera de tu cuerpo tener Ni tu padre ni tu madre te quieren conmigo Pues hagamos el amor por el teléfono
A31: =AGREEMENT!A112 -> BALADA | B31: =AGREEMENT!E112 -> Cuando escriba tu nombre en la arena blanca con fondo azul Cuando mire el cielo, en la forma cruel de una nube gris aparezcas tú Una tarde suba una alta loma, mire el pasado, sabrás que no te he olvidado
A32: =AGREEMENT!A73 -> REGAETTON | B32: =AGREEMENT!E73 -> Baby Suena tu canción y tú no estás aquí, a mi lao Yo sé que no debo, aunque te pienso demasiao Qué rico esos días cuando estábamos tragao' Tú y yo somos fuego cuando estamos emborrachao' Suena tu canción y tú no estás aquí, a mi lao Yo sé que no debo, aunque te pienso demasiao Quererte es tan fácil y a la vez tan complicao Mirando al teléfono, pero no me has llamao Baby, wow Me gustas demasiado Bebé Baby, wow Te pienso demasiao
A33: =AGREEMENT!A124 -> BALADA | B33: =AGREEMENT!E124 -> Cuanto daría por gritarles nuestro amor Decirles que al cerrar la puerta nos amamos sin control Que despertamos abrazados Con ganas de seguir amándonos Pero es que en realidad no aceptan nuestro amor
A34: =AGREEMENT!A555 -> BALADA | B34: =AGREEMENT!E555 -> Todo lo que pasa es relativo. Pero, cada vez que estoy contigo. El tiempo se detiene. Y desapareces. Y tú me das todo lo demás. Yo quiero estar donde tú estás. Amor eres tú. Solo tú. Y tú me das todo lo demás. Yo quiero estar donde tú estás. Amor eres tú. Ninguno como tú. Todo lo que dice un solo beso. Hace que se rinda el universo. Como hacen los dioses. Al caer la noche. Para qué correr si no hay apuro. Si es que cada vez que estamos juntos. El tiempo se detiene. Y desapareces
A35: =AGREEMENT!A594 -> BALADA | B35: =AGREEMENT!E594 -> Viejo, mi querido viejo Ahora ya caminas lerdo Como perdonando el viento Yo soy tu sangre, mi viejo Soy tu silencio y tu tiempo Él tiene los ojos buenos Y una figura pesada La edad se le vino encima Sin carnaval ni comparsa
A36: =AGREEMENT!A431 -> BALADA | B36: =AGREEMENT!E431 -> Qué difícil es hablarte y tú no comprender. Conversar lo mismo y enfadarnos otra vez. Porque no me dejas que me vaya por un tiempo. Sin decirme que al momento. Te vas a quitar la vida si me voy
A37: =AGREEMENT!A599 -> REGAETTON | B37: =AGREEMENT!E599 -> Vo'a llevarte pa' PR, mami, pa' que vea' cómo es que se perrea. Tráete a tu amiga si te gusta la idea. Dile que esta noche vamo' a janguear. Que rico la vamo' a pasar. Aquí nadie se va a casar. Pero tú te va' a querer quedar, yeah
A38: =AGREEMENT!A511 -> BALADA | B38: =AGREEMENT!E511 -> Siempre serás la niña que me llena el alma. Como un mar inquieto, como un mar en calma. Siempre tan lejana como el horizonte. Gritando en el silencio tu nombre en mis labios. Solo queda el eco de mi desengaño.
A39: =AGREEMENT!A135 -> BALADA | B39: =AGREEMENT!E135 -> Decir "te quiero", decir "amor" No significa nada Las palabras sinceras, las que tienen valor Son las que salen del alma Y en mi alma nacen Solo palabras blancas. Preguntas sin respuesta Llenas de esperanza Un amor como el mío no se puede ahogar Como una piedra en un río Un amor como el mío no se puede acabar Ni estando lejos te olvido
A40: =AGREEMENT!A74 -> REGAETTON | B40: =AGREEMENT!E74 -> Baby, ¿por qué tú sigue' ahí, tan incómoda ahí? Escápate conmigo, no' vamo' del party Tú queriendo irte y él no te deja ir (¿qué?) Tanto gym, pero él no te hace venir
A41: =AGREEMENT!A629 -> REGAETTON | B41: =AGREEMENT!E629 -> Y puede ser que sí, o puede ser que no. Al final, terminaremos besándonos. ¿Qué será de mí? ¿O qué será de ti? No preguntemos, al final solo sabe Dios. Tengo tu cuerpo en mi mente. Muy dentro plasmado (muy dentro plasmado)
A42: =AGREEMENT!A619 -> BALADA | B42: =AGREEMENT!E619 -> Y en mi soledad Cuando quiera yo salir a buscarte Cuando miras a la Luna y no está Cuando lleguen los humanos a Marte Mira dejaré la vida pasar Cuando tengas la intención de casarte Cuando sepas que ya no puedo más Besarás con esa obra de arte A este loco que ya no puede más
A43: =AGREEMENT!A139 -> BALADA | B43: =AGREEMENT!E139 -> Dejaré mi tierra por ti dejaré mis campos y me iré lejos de aquí. Cruzaré llorando el jardín y con tus recuerdos partiré lejos de aquí. De día viviré pensando en tus sonrisas de noche las estrellas me acompañarán.
A44: =AGREEMENT!A680 -> REGAETTON | B44: =AGREEMENT!E680 -> Yo sé que acabo de conocerte Y es muy rápido pa' tenerte Yo, lo que quiero, es complacerte Tú, tranquila, déjate llevar Dime si conmigo quieres hacer travesuras Que se ha vuelto una locura Y tú estás bien dura No me puedo contener
A45: =AGREEMENT!A35 -> BALADA | B45: =AGREEMENT!E35 -> Amiga, tú, la misma de ayer La incondicional La que no espera nada Tú, la misma de ayer La que no supe amar (no sé por qué)
A46: =AGREEMENT!A147 -> REGAETTON | B46: =AGREEMENT!E147 -> Dile que bailando te conocí, cuéntale Dile que esta noche me quieres ver, cuéntale Cuéntale que beso mejor que él, cuéntale Dile que esta noche tú me va' a ver, cuéntale
A47: =AGREEMENT!A541 -> BALADA | B47: =AGREEMENT!E541 -> Te voy a cambiar el nombre Para guardar el secreto Porque te amo y me amas Y a alguien debemos respeto Te voy a cambiar el nombre En base a lo que has traído Ahora te llamarás Gloria Lo tienes bien merecido Y hemos de darnos un beso
A48: =AGREEMENT!A318 -> BALADA | B48: =AGREEMENT!E318 -> Mi amor no tiene esperanza Aunque te esperara Mi corazon se lanza Un fantasma corpo real Mi amor no tiene venganza Aunque te matara Este viejo no se cansa Siempre te persigara Así que Fe y amor no necesita esperanza Ven amor aquí Feo amor no grita en mi lancha Alrededor de ti
A49: =AGREEMENT!A29 -> BALADA | B49: =AGREEMENT!E29 -> Amanecer con él. A mi costado no es igual que estar contigo. No es que esté mal, ni hablar. Pero le falta madurar, es casi un niño. Blanco como el yogurt. Sin ese toro que tu llevas en el pecho. Fragilidad de flor.Nada que ver con mi perverso favorito. Sin tus uñas arañándome la espalda. Sin tus manos que me estrujan todo cambia. Sin tu lengua envenenado mi garganta. Sin tus dientes que torturan y endulzan yo no siento nada. Hacer el amor con otro, no no no. No es la misma cosa, no hay estrellas de color rosa. No destilan los poros del cuerpo. Ambrosía salpicada de te quieros
A50: =AGREEMENT!A63 -> BALADA | B50: =AGREEMENT!E63 -> Ay Amor Tú eres mi religión Tú eres luz, tú eres mi sol Abre el corazón Abre el corazón Hace tanto tiempo, corazón Viví el dolor y en el olvido Ay, amor, eres mi bendición, mi religión Eres mi sol que cura el frío
A51: =AGREEMENT!A51 -> REGAETTON | B51: =AGREEMENT!E51 -> Aquel día te vi y tu energía sentí Desde eso no te quiero lejos de mí (Lejos de mí) Sé que no sabes de mí y no te puedo mentir Lo que dicen en la calle sobre mí (Sobre mí) Y no te voy a negar Estamos claro' y ya No te lo voy a negar (Jaja, no te lo puedo negar) Estamos claro' y ya (Jaja, que estamos claro', que estamos claro')
A52: =AGREEMENT!A624 -> BALADA | B52: =AGREEMENT!E624 -> Y me explicaba Que el amor es una cosa Que se da de pronto en forma natural, lleno de fuego Si lo forzás se marchita Sin tener principio, llega a su final Ahora, tal vez, lo puedas entender Que si me tocas se quema mi piel Ahora, tal vez, lo puedas entender Y no te vuelvas si no quieres ver
A53: =AGREEMENT!A524 -> BALADA | B53: =AGREEMENT!E524 -> Sufrimos los dos y logramos vencer Las fuerzas de la adversidad Y juntos logramos al fin el tener La dicha que alcanza un amor de verdad Dos, somos dos, solo dos a sentir Un amor de verdad en el corazón Dos, somos dos, solo dos a luchar Por llegar hasta el fuego de la pasión
A54: =AGREEMENT!A56 -> REGAETTON | B54: =AGREEMENT!E56 -> Así son las cosa', lírica mala, mañosa Belicosa, y super maliciosa Del agua mansa líbralo, Dios Je, je, que aquí nadie sabe lo que pasó
A55: =AGREEMENT!A397 -> BALADA | B55: =AGREEMENT!E397 -> Perdona mi franqueza que tal vez Juzgues descaro Yo sé que voy a herirte por decirte Lo que siento Espero que comprendas que es mejor Que hablemos claro Debemos separarnos porque amor Ya no te tengo
A56: =AGREEMENT!A563 -> BALADA | B56: =AGREEMENT!E563 -> Tú eres la tristeza de mis ojos. Que lloran en silencio por tu amor. Me miro en el espejo y veo en mi rostro. El tiempo que he sufrido por tu adiós. Obligo a que te olvide el pensamiento. Pues, siempre estoy pensando en el ayer. Prefiero estar dormida que despierto. De tanto que me duele que no estés.
A57: =AGREEMENT!A514 -> BALADA | B57: =AGREEMENT!E514 -> Sin saber de la cuenta regresiva, pienso Que aunque no he vuelto a ser el mismo, y lo confieso Espero que el perdón esté en tu mente, y yo te rezo Pero aunque soy sincero y lo prometo, no me miras Después abres la puerta y digo: "si te vas no vuelvas"
A58: =AGREEMENT!A351 -> REGAETTON | B58: =AGREEMENT!E351 -> No me importa que usted sea mayor que yo, hoy la quiero en mi cama Y no malinterprete mi intención, es que no aguanto las gana' Por eso he venido a decírselo, que hoy la quiero en mi cama Si no estás dispuesta, ya dímelo, es que no aguanto las gana' Dame un chance No me importa que usted sea mayor que yo, oye Te quiero aquí aunque tenga' mil amores Yo creo en el destino, oye Tú sabes que Dios tiene sus razones Eres mayor que yo, oye Te quiero aquí aunque tenga' mil amores Yo creo en el destino, oye Tú sabes que Dios tiene sus razones (¡Fuimo'!) Avanza, vámono' y déjemono' de blablablá Suelta la cartera pa' la cama con el chachachá Te miro y me mira', te me pego pero no haces na' Dime por qué, por qué (¡Vamo'!)
A59: =AGREEMENT!A257 -> REGAETTON | B59: =AGREEMENT!E257 -> Kinky, nasty, y aunque sea fancy Se pone cranky si lo hago romantic Le gusta el sexo en exceso Y en el proceso, me pide un beso La veo en la disco casi todos los weekend' Al parecer, en su casa no hay quien la frene El vacilón de ella comienza desde el jueve' Tiene un amigo en el baño, al parecer no la entretiene
A60: =AGREEMENT!A549 -> REGAETTON | B60: =AGREEMENT!E549 -> Tengo un delincuente en mi habitación A vece' me lo mete al pelo y a vece' con condón Tengo un delincuente en mi habitación Me lo mete en la cocina y a vece' hasta en el balcón Tengo un delincuente en mi habitación A vece' me lo mete al pelo y a vece' con condón, ah (brr) Tengo un delincuente en mi habitación (to' los bellacos y to'a las bellacas conmigo) Me lo mete en la cocina y a vece' en el balcón
A61: =AGREEMENT!A177 -> REGAETTON | B61: =AGREEMENT!E177 -> Ella está casi, casi soltera Un corillo de bandoleras Quieren perreo la noche entera Sin cojones le tiene si se enteran Porque está casi, casi soltera Un corillo de bandoleras Quieren perreo la noche entera Sin cojones le tiene si se enteran, yeh
A62: =AGREEMENT!A117 -> REGAETTON | B62: =AGREEMENT!E117 -> Cuando nos vimos de frente delante de tanta gente. Fui cómplice de un acto indecente. La más divina, del Instagram. Mami eres tú ya no me importan las demás
A63: =AGREEMENT!A472 -> REGAETTON | B63: =AGREEMENT!E472 -> Relájate. No ha pasado nada y los nervios ahora te hacen reír. Creo que cuando me hablas no te quieres despedir. No me conformaré con mirarte na má'. Revélate pa llevarte a lo intimo ya
A64: =AGREEMENT!A61 -> BALADA | B64: =AGREEMENT!E61 -> Aún me quedan en mis manos primaveras Para colmarte de caricias todas nuevas Que morirían en mis manos si te fueras Espera un poco, un poquito más Para llevarte mi felicidad Espera un poco, un poquito más Me moriría si te vas
A65: =AGREEMENT!A585 -> BALADA | B65: =AGREEMENT!E585 -> Tú, la misma, siempre tú Amistad, ternura, ¿qué sé yo? Tú, mi sombra has sido tú La historia de un amor Que no fue nada Tú, mi eternamente tú Un hotel, tu cuerpo y un adiós Tú, mi oculta amiga, tú Un golpe de pasión Amor de madrugada
A66: =AGREEMENT!A455 -> BALADA | B66: =AGREEMENT!E455 -> Quédate un momento así No mires hacia mí Que no podría aguantar Si clavas tu mirada Que me hiela el cuerpo Me ha pasado antes Que no puedo hablar
A67: =AGREEMENT!A136 -> BALADA | B67: =AGREEMENT!E136 -> Decir te quiero, decir amor, no significa nada, las palabras sinceras, las que tienen valor, son las que salen del alma, y en mi alma nacen solo palabras blancas, preguntas sin respuesta, llenas de esperanza.
A68: =AGREEMENT!A656 -> BALADA | B68: =AGREEMENT!E656 -> Ya me estoy acostumbrando A tu sonrisa Dime si tienes planes ¿Qué vas a hacer por el resto de tu vida? Por el resto de tu vida Por el resto de tu vida Quiero saber qué vas a hacer por el resto de tu vida
A69: =AGREEMENT!A243 -> REGAETTON | B69: =AGREEMENT!E243 -> Hoy es noche de sexo Voy a devorarte, nena linda (Predi) Hoy es noche de sexo Y voy a cumplir tus fantasías (¿Cómo?) Hoy es noche de sexo Ay, voy a devorarte, nena linda Hoy es noche de sexo Lo juro por Dios que esta noche serás mía (¿Qué?) Quiero arrancarte la tela, con cautela Mi piel canela enseguida pela Ella es la protagonista de mi novela Mi cinderella conmigo es que vuela Póngase romántica, please, dame un kiss No cometa un desliz Ella combina la calle con la moda de París La miss sigue matando en el país
A70: =AGREEMENT!A522 -> BALADA | B70: =AGREEMENT!E522 -> Suelta mi mano ya por favor Entiende que me tengo que ir Si ya no sientes más este amor No tengo nada mas que decir No digas nada ya por favor Te entiendo pero entiéndeme a mí Cada palabra aumenta el dolor Y una lagrima quiere salir
A71: =AGREEMENT!A155 -> BALADA | B71: =AGREEMENT!E155 -> Duele y es difícil confesar. Se que llego el momento lento de aceptar. De llamar y decirte fui una tonta, amor, perdóname. De correr a pedirte que me abraces una y otra vez. Que no quise perderte, dejarte.
A72: =AGREEMENT!A566 -> BALADA | B72: =AGREEMENT!E566 -> Tú eres mi amor, mi alegría La verdad de mi vida Mi bebe que me calma el alma con risas Tú eres mi refugio y mi verdad
A73: =AGREEMENT!A346 -> REGAETTON | B73: =AGREEMENT!E346 -> No la contratan pa' bailar porque se roba el show. No quiere ser modelo porque eso le aburrió. No puede ser locutora porque con su voz enamoró. Tendría que ser ladrona porque te roba hasta el corazón.
A74: =AGREEMENT!A655 -> BALADA | B74: =AGREEMENT!E655 -> Ya me enteré que hay alguien nuevo acariciando tu piel, algún idiota al que quieres convencer que tú y yo somos pasado. Ya me enteré que soy el malo y todo el mundo te cree, que estás mejor desde que ya no me ves.
A75: =AGREEMENT!A517 -> BALADA | B75: =AGREEMENT!E517 -> Sólo quedan las ganas de llorar Al ver que nuestro amor se aleja Frente a frente, bajamos la mirada Pues ya no queda nada de qué hablar, nada Sólo quedan las ganas de llorar Al ver que nuestro amor se aleja Frente a frente, bajamos la mirada Pues ya no queda nada de qué hablar, nada
A76: =AGREEMENT!A534 -> BALADA | B76: =AGREEMENT!E534 -> Te extraño Como se extrañan las noches sin estrellas Como se extrañan las mañanas bellas No estar contigo Por Dios que me hace daño Te extraño Cuando camino, cuando lloro Cuando río Cuando el sol brilla Y cuando hace mucho frío Porque te siento Como algo muy mío Por Dios, te extraño Como los árboles extrañan el otoño En esas noches que no concilio el sueño No te imaginas amor cuánto te extraño
A77: =AGREEMENT!A12 -> REGAETTON | B77: =AGREEMENT!E12 -> "Ella no era así, ella no era así No sé quién la dañó Ella no era así, ella no era así No sé quién la dañó"
A78: =AGREEMENT!A384 -> REGAETTON | B78: =AGREEMENT!E384 -> Otro sunset bonito que veo en San Juan Disfrutando de todas esas cosas que extrañan los que se van (van, van) Disfrutando de noche' de esas que ya no se dan (dan, dan) Que ya no se dan (dan) Pero queriendo volver a la última vez Que a los ojos te miré Y contarte las cosas que no te conté (te parece' a mi crush, jaja) Y tirarte la' foto' que no te tiré (acho, jura'o te ves bien linda, déjame tirarte una foto)
A79: =AGREEMENT!A667 -> BALADA | B79: =AGREEMENT!E667 -> Yo era feliz contigo Vida mía Tú eras principio y fin De mi alegria Yo te creía fiel Como la luna Que acude a protegernos Cada día Yo era feliz contigo Vida mía Tú eras mi perro fiel Yo era tu guía Hasta que desperté De mi locura Y pude comprender Que me mentías Todo se derrumbo Dentro de mí, dentro de mí Hasta mi aliento ya Me sabe a hiel, me sabe a hiel
A80: =AGREEMENT!A440 -> REGAETTON | B80: =AGREEMENT!E440 -> Que no se enamore, ella está pal' juego
A81: =AGREEMENT!A265 -> REGAETTON | B81: =AGREEMENT!E265 -> La mano arriba, cintura sola (¡danza!) Da media vuelta, danza kuduro (¡danza!) No te canse' ahora, que esto solo empieza (¡danza!) Mueve la cabeza (¡danza!) Oi oi oi Oi oi oi oi É pra quebrar kuduro Vamos dançar kuduro
A82: =AGREEMENT!A260 -> REGAETTON | B82: =AGREEMENT!E260 -> La jeepeta de 300, no perdiste el tiempo
A83: =AGREEMENT!A334 -> BALADA | B83: =AGREEMENT!E334 -> Mirándote a los ojos juraría. Que tienes algo nuevo que contarme. Empieza ya, mujer, no tengas miedo. Quizá para mañana sea tarde. Quizá para mañana sea tarde ¿Y cómo es él? ¿En qué lugar se enamoró de ti? ¿De dónde es? ¿A qué dedica el tiempo libre?
A84: =AGREEMENT!A593 -> BALADA | B84: =AGREEMENT!E593 -> Ven y cuéntame la verdad Ten piedad Y dime por qué No, no, no, oh ¿Cómo fue que me dejaste de amar? Yo aún podía soportar Tu tanta falta de querer
A85: =AGREEMENT!A42 -> BALADA | B85: =AGREEMENT!E42 -> Amor, amor Que te pintas de cualquier color Tan profundo como el viento Tan lejano como el tiempo Y tan cierto como el sol
A86: =AGREEMENT!A444 -> BALADA | B86: =AGREEMENT!E444 -> Que te quedarás conmigo una vida entera Que contigo: adiós inviernos, solo primavera Que las olas son de magia y no de agua salada Yo te creo todo y tú no me das nada, tú no me das nada
A87: =AGREEMENT!A186 -> BALADA | B87: =AGREEMENT!E186 -> En el canto de las olas Encontré un rumor de luz Por un canto de gaviotas Supe que allí estabas tú Despidiendo últimamente Todo lo que sucedió Hoy, saludo mi presente Y gusto de este dulce adiós
A88: =AGREEMENT!A634 -> REGAETTON | B88: =AGREEMENT!E634 -> Y si hoy llevo la ropa fake, es porque soy la más real Bitch, me creo Dapper Dan Me doy un flow de paca, me veo original Soy la marca más cara que tú no vas a poder capear
A89: =AGREEMENT!A156 -> BALADA | B89: =AGREEMENT!E156 -> Duelen más tus cosas buenas cuando estás ausente. Yo sé que es demasiado tarde para remediar. No me queda bien valerme de diez mil excusas. Cuando definitivamente sé que ahora te vas
A90: =AGREEMENT!A464 -> REGAETTON | B90: =AGREEMENT!E464 -> Quiero ver bailar tu pelo Quiero ser tu ritmo (uh oh, uh oh) Que le enseñes a mi boca (uh oh, uh oh) Tus lugares favoritos (favoritos, favoritos baby) Déjame sobrepasar tus zonas de peligro (uh oh, uh oh) Hasta provocar tus gritos (uh oh, uh oh) Y que olvides tu apellido (dirididi Daddy)
A91: =AGREEMENT!A111 -> BALADA | B91: =AGREEMENT!E111 -> Cuando amanece, tu lindura. Cualquier constelación se pone insegura. Tu belleza huele a mañana. Y me da de comer. Durante toda la semana. Tus ojos hacen magia, son magos. Los abriste y ahora se reflejan las montañas. En los lagos, la única verdad absoluta es. Que cuando naciste tu. A los arboles le nacieron frutas. Naranja dulce. Siembra de querubes. Como el sol tenia miedo. Se escondió en una nube. Hoy el sol no hace falta, esta en receso. La vitamina d me la das tú con un beso
A92: =AGREEMENT!A577 -> REGAETTON | B92: =AGREEMENT!E577 -> Tu tatuaje de Luna en el tobillo. Tu piel color perla, ojito' con brillo. Los polvito' escondido', no me olvido. Enamora'itos, éramos niño'. Y se sentía real, todo era real. Si te lo hice en el prom, baby, ¿cómo olvidar?
A93: =AGREEMENT!A138 -> BALADA | B93: =AGREEMENT!E138 -> Déjame amarte como si el amor viviera y aunque no quiera si quererlo piensa en mí qué importa si para enamorarme basta una hora pasa ligera la maldita primavera
A94: =AGREEMENT!A676 -> BALADA | B94: =AGREEMENT!E676 -> Yo quiero hacer vida contigo. Ser amante, ser amigos. Y ser la historia favorita. Que comparten los testigos. Que conocen lo que somos. Y lo que antes fuimos
A95: =AGREEMENT!A377 -> REGAETTON | B95: =AGREEMENT!E377 -> Nunca se deja ver (nunca se deja ver) No sabe disimular (no sabe disimular) Tiene lo suyo y le va bien Pero de noche conmigo le gusta portarse mal Llega y lo que quiere es pecar Música que quiere bailar (la presión) Ya no la paro, a veces mira raro y Se hace la que no me conoce
A96: =AGREEMENT!A141 -> REGAETTON | B96: =AGREEMENT!E141 -> Despacito Quiero respirar tu cuello despacito Deja que te diga cosas al oído Para que te acuerdes si no estás conmigo Despacito Quiero desnudarte a besos despacito Firmar las paredes de tu laberinto Y hacer de tu cuerpo todo un manuscrito (sube, sube, sube) (Sube, sube) Oh
A97: =AGREEMENT!A214 -> REGAETTON | B97: =AGREEMENT!E214 -> Ey, baby, no, no No ves que me estoy muriendo Por que un ratito me regales tu atención, oh-oh-oh Estoy perdido en el azul de tus ojos, yeh Nena maldición, nena maldición Yo ni te conozco, pero jugaría con vos Nena maldición, ey, nena maldición, yo' Yo ni la conozco, pero jugaría con vos
A98: =AGREEMENT!A450 -> BALADA | B98: =AGREEMENT!E450 -> Qué triste fue decirnos adiós Cuando nos adorábamos más Hasta la golondrina emigró Presagiando el final Qué triste luce todo sin ti Los mares de las playas se van Se tiñen los colores de gris Hoy todo es soledad No sé si vuelva a verte después No sé qué de mi vida será Sin el lucero azul de tú ser Que no me alumbra ya
A99: =AGREEMENT!A662 -> REGAETTON | B99: =AGREEMENT!E662 -> Ya no tiene excusa Hoy salió con su amiga Dizque para' matar la tusa (tusa) Que porque un hombre le pagó mal Está dura y abusa Se cansó de ser buena Ahora es ella quien los usa Que porque un hombre le pagó mal Ya no se le ve sentimental Dice que por otro man no llora (llora), no Ya no tiene excusa Hoy salió con su amiga Dizque para' matar la tusa (tusa) Que porque un hombre le pagó mal Está dura y abusa Se cansó de ser buena Ahora es ella quien los usa Que porque un hombre le pagó mal Ya no se le ve sentimental Dice que por otro man no llora (llora), no
A100: =AGREEMENT!A169 -> BALADA | B100: =AGREEMENT!E169 -> El muchacho de los ojos tristes Vive solo y necesita amor Como el aire necesita verme Como el sol lo necesito yo El muchacho de los ojos tristes Ha encontrado al fin una razón Para hacer que su mirada ría Con mis besos y mi gran amor
...

Sheet Coeficiente de Correlación Intr
A1: Hoja A | B1: Hoja B | C1: Hoja C | D1: Desacuerdo de cada fila | F1: Promedio desacuedo | G1: Varianza total | H1: ICC | J1: Escala | K1: Interpretación
A2: =A!B2 -> -1 | B2: =B!B2 -> -2 | C2: ='C'!B2 -> -1 | D2: =_xlfn.VAR.S(A2:C2) -> 0.33333333 | F2: =AVERAGE(D2:D691) -> 0.74057971 | G2: =_xlfn.VAR.S(A2:C691) -> 3.0207793 | H2: =1 - (F2/G2) -> 0.75483819 | J2: >0.40 | K2: Pobre
A3: =A!B3 -> 2 | B3: =B!B3 -> 2 | C3: ='C'!B3 -> 2 | D3: =_xlfn.VAR.S(A3:C3) -> 0 | J3: 0.40 - 0.59 | K3: Regular
A4: =A!B4 -> -2 | B4: =B!B4 -> 0 | C4: ='C'!B4 -> -1 | D4: =_xlfn.VAR.S(A4:C4) -> 1 | J4: 0.60 - 0.74 | K4: Bueno
A5: =A!B5 -> 2 | B5: =B!B5 -> 2 | C5: ='C'!B5 -> 2 | D5: =_xlfn.VAR.S(A5:C5) -> 0 | J5: 0.75 - 1 | K5: Excelente
A6: =A!B6 -> 0 | B6: =B!B6 -> 2 | C6: ='C'!B6 -> 2 | D6: =_xlfn.VAR.S(A6:C6) -> 1.3333333
A7: =A!B7 -> 1 | B7: =B!B7 -> 0 | C7: ='C'!B7 -> 2 | D7: =_xlfn.VAR.S(A7:C7) -> 1
A8: =A!B8 -> -1 | B8: =B!B8 -> -2 | C8: ='C'!B8 -> -2 | D8: =_xlfn.VAR.S(A8:C8) -> 0.33333333
A9: =A!B9 -> 2 | B9: =B!B9 -> 2 | C9: ='C'!B9 -> 2 | D9: =_xlfn.VAR.S(A9:C9) -> 0
A10: =A!B10 -> -2 | B10: =B!B10 -> -2 | C10: ='C'!B10 -> -1 | D10: =_xlfn.VAR.S(A10:C10) -> 0.33333333
A11: =A!B11 -> -2 | B11: =B!B11 -> -2 | C11: ='C'!B11 -> 0 | D11: =_xlfn.VAR.S(A11:C11) -> 1.3333333
A12: =A!B12 -> 1 | B12: =B!B12 -> 1 | C12: ='C'!B12 -> -1 | D12: =_xlfn.VAR.S(A12:C12) -> 1.3333333
A13: =A!B13 -> 2 | B13: =B!B13 -> 2 | C13: ='C'!B13 -> 2 | D13: =_xlfn.VAR.S(A13:C13) -> 0
A14: =A!B14 -> 2 | B14: =B!B14 -> 2 | C14: ='C'!B14 -> 2 | D14: =_xlfn.VAR.S(A14:C14) -> 0
A15: =A!B15 -> 2 | B15: =B!B15 -> 2 | C15: ='C'!B15 -> 2 | D15: =_xlfn.VAR.S(A15:C15) -> 0
A16: =A!B16 -> 2 | B16: =B!B16 -> 2 | C16: ='C'!B16 -> 2 | D16: =_xlfn.VAR.S(A16:C16) -> 0
A17: =A!B17 -> 2 | B17: =B!B17 -> 1 | C17: ='C'!B17 -> 2 | D17: =_xlfn.VAR.S(A17:C17) -> 0.33333333
... A691: =A!B691 -> 2 | B691: =B!B691 -> 2 | C691: ='C'!B691 -> 2 | D691: =_xlfn.VAR.S(A691:C691) -> 0
A692: =A!B692
A693: =A!B693
